[1,["cb79034c-e2c4-4999-af19-431dffcf01f1@6c48a"],["_textureSource"],["cc.SpriteFrame","cc.SpriteAtlas"],0,[[[{"name":"icon_card","spriteFrames":["5D_PZ_icon_b","0266311c-6817-4c26-8778-c477c5891ca0@12543","5D_PZ_icon_platinum","0266311c-6817-4c26-8778-c477c5891ca0@d903b","5D_PZ_icon_r","0266311c-6817-4c26-8778-c477c5891ca0@b48f5","5D_PZ_icon_p","0266311c-6817-4c26-8778-c477c5891ca0@009ae","5D_PZ_icon_y","0266311c-6817-4c26-8778-c477c5891ca0@40269","5D_ZY_big_career_01","0266311c-6817-4c26-8778-c477c5891ca0@0befd","5D_ZY_big_career_02","0266311c-6817-4c26-8778-c477c5891ca0@21572","5D_ZY_big_career_03","0266311c-6817-4c26-8778-c477c5891ca0@26093","5D_ZY_big_career_04","0266311c-6817-4c26-8778-c477c5891ca0@98ee2","5D_TY_stars_b","0266311c-6817-4c26-8778-c477c5891ca0@773cc","5D_TY_stars_c","0266311c-6817-4c26-8778-c477c5891ca0@05621","5D_TY_stars_p","0266311c-6817-4c26-8778-c477c5891ca0@5f8bb","5D_TY_stars_pp","0266311c-6817-4c26-8778-c477c5891ca0@7fd6c","5D_TY_stars_r","0266311c-6817-4c26-8778-c477c5891ca0@e12ca","5D_TY_stars_w","0266311c-6817-4c26-8778-c477c5891ca0@f5fcb","5D_TY_stars_y","0266311c-6817-4c26-8778-c477c5891ca0@af00a","5D_ZY_career_01","0266311c-6817-4c26-8778-c477c5891ca0@2c9e1","5D_ZY_career_02","0266311c-6817-4c26-8778-c477c5891ca0@9f188","5D_ZY_career_03","0266311c-6817-4c26-8778-c477c5891ca0@67a4c","5D_ZY_career_04","0266311c-6817-4c26-8778-c477c5891ca0@37233","5D_ZY_career_all","0266311c-6817-4c26-8778-c477c5891ca0@dc7bf","5D_ZY_camp_01","0266311c-6817-4c26-8778-c477c5891ca0@6e5e9","5D_ZY_camp_02","0266311c-6817-4c26-8778-c477c5891ca0@cd823","5D_ZY_camp_03","0266311c-6817-4c26-8778-c477c5891ca0@16d4e","5D_ZY_camp_04","0266311c-6817-4c26-8778-c477c5891ca0@13926","5D_ZY_camp_05","0266311c-6817-4c26-8778-c477c5891ca0@e1484","5D_ZY_camp_06","0266311c-6817-4c26-8778-c477c5891ca0@1de47","5D_ZY_camp_07","0266311c-6817-4c26-8778-c477c5891ca0@342c4","5D_ZY_camp_08","0266311c-6817-4c26-8778-c477c5891ca0@98880","5D_PZ_small_icon_b","0266311c-6817-4c26-8778-c477c5891ca0@d2679","5D_PZ_small_icon_p","0266311c-6817-4c26-8778-c477c5891ca0@62b66","5D_PZ_small_icon_platinum","0266311c-6817-4c26-8778-c477c5891ca0@a1ccd","5D_PZ_small_icon_r","0266311c-6817-4c26-8778-c477c5891ca0@20a70","5D_PZ_small_icon_y","0266311c-6817-4c26-8778-c477c5891ca0@f80d2","5D_TY_lineup_b","0266311c-6817-4c26-8778-c477c5891ca0@b10f2","5D_TY_lineup_y","0266311c-6817-4c26-8778-c477c5891ca0@8088d","5D_TY_lineup_p","0266311c-6817-4c26-8778-c477c5891ca0@1c4eb","5D_TY_lineup_g","0266311c-6817-4c26-8778-c477c5891ca0@6f666","5D_TY_lineup_r","0266311c-6817-4c26-8778-c477c5891ca0@af7ba"]}],[1],0,[],[],[]],[[{"name":"5D_PZ_icon_p","rect":{"x":103,"y":104,"width":96,"height":85},"offset":{"x":-1,"y":0.5},"originalSize":{"width":100,"height":88},"rotated":true,"capInsets":[0,0,0,0],"vertices":{"rawPosition":[],"indexes":[],"uv":[],"nuv":[],"minPos":{"x":0,"y":0,"z":0},"maxPos":{"x":0,"y":0,"z":0}},"packable":true,"pixelsToUnit":100,"pivot":{"x":0.5,"y":0.5},"meshType":0}],[0],0,[0],[0],[0]],[[{"name":"5D_TY_stars_c","rect":{"x":2,"y":266,"width":60,"height":58},"offset":{"x":0,"y":0},"originalSize":{"width":60,"height":60},"rotated":false,"capInsets":[0,0,0,0],"vertices":{"rawPosition":[],"indexes":[],"uv":[],"nuv":[],"minPos":{"x":0,"y":0,"z":0},"maxPos":{"x":0,"y":0,"z":0}},"packable":true,"pixelsToUnit":100,"pivot":{"x":0.5,"y":0.5},"meshType":0}],[0],0,[0],[0],[0]],[[{"name":"5D_ZY_big_career_01","rect":{"x":192,"y":104,"width":86,"height":85},"offset":{"x":0,"y":-0.5},"originalSize":{"width":86,"height":86},"rotated":false,"capInsets":[0,0,0,0],"vertices":{"rawPosition":[],"indexes":[],"uv":[],"nuv":[],"minPos":{"x":0,"y":0,"z":0},"maxPos":{"x":0,"y":0,"z":0}},"packable":true,"pixelsToUnit":100,"pivot":{"x":0.5,"y":0.5},"meshType":0}],[0],0,[0],[0],[0]],[[{"name":"5D_PZ_icon_b","rect":{"x":2,"y":2,"width":99,"height":85},"offset":{"x":-0.5,"y":0.5},"originalSize":{"width":100,"height":88},"rotated":false,"capInsets":[0,0,0,0],"vertices":{"rawPosition":[],"indexes":[],"uv":[],"nuv":[],"minPos":{"x":0,"y":0,"z":0},"maxPos":{"x":0,"y":0,"z":0}},"packable":true,"pixelsToUnit":100,"pivot":{"x":0.5,"y":0.5},"meshType":0}],[0],0,[0],[0],[0]],[[{"name":"5D_ZY_camp_04","rect":{"x":316,"y":308,"width":52,"height":53},"offset":{"x":0,"y":0.5},"originalSize":{"width":56,"height":56},"rotated":false,"capInsets":[0,0,0,0],"vertices":{"rawPosition":[],"indexes":[],"uv":[],"nuv":[],"minPos":{"x":0,"y":0,"z":0},"maxPos":{"x":0,"y":0,"z":0}},"packable":true,"pixelsToUnit":100,"pivot":{"x":0.5,"y":0.5},"meshType":0}],[0],0,[0],[0],[0]],[[{"name":"5D_ZY_camp_03","rect":{"x":2,"y":328,"width":52,"height":53},"offset":{"x":0,"y":0.5},"originalSize":{"width":56,"height":56},"rotated":false,"capInsets":[0,0,0,0],"vertices":{"rawPosition":[],"indexes":[],"uv":[],"nuv":[],"minPos":{"x":0,"y":0,"z":0},"maxPos":{"x":0,"y":0,"z":0}},"packable":true,"pixelsToUnit":100,"pivot":{"x":0.5,"y":0.5},"meshType":0}],[0],0,[0],[0],[0]],[[{"name":"5D_TY_lineup_p","rect":{"x":398,"y":243,"width":27,"height":44},"offset":{"x":-0.5,"y":0},"originalSize":{"width":28,"height":44},"rotated":false,"capInsets":[0,0,0,0],"vertices":{"rawPosition":[],"indexes":[],"uv":[],"nuv":[],"minPos":{"x":0,"y":0,"z":0},"maxPos":{"x":0,"y":0,"z":0}},"packable":true,"pixelsToUnit":100,"pivot":{"x":0.5,"y":0.5},"meshType":0}],[0],0,[0],[0],[0]],[[{"name":"5D_ZY_camp_06","rect":{"x":130,"y":351,"width":52,"height":53},"offset":{"x":0,"y":0.5},"originalSize":{"width":56,"height":56},"rotated":false,"capInsets":[0,0,0,0],"vertices":{"rawPosition":[],"indexes":[],"uv":[],"nuv":[],"minPos":{"x":0,"y":0,"z":0},"maxPos":{"x":0,"y":0,"z":0}},"packable":true,"pixelsToUnit":100,"pivot":{"x":0.5,"y":0.5},"meshType":0}],[0],0,[0],[0],[0]],[[{"name":"5D_PZ_small_icon_r","rect":{"x":398,"y":181,"width":58,"height":27},"offset":{"x":0,"y":0.5},"originalSize":{"width":58,"height":28},"rotated":true,"capInsets":[0,0,0,0],"vertices":{"rawPosition":[],"indexes":[],"uv":[],"nuv":[],"minPos":{"x":0,"y":0,"z":0},"maxPos":{"x":0,"y":0,"z":0}},"packable":true,"pixelsToUnit":100,"pivot":{"x":0.5,"y":0.5},"meshType":0}],[0],0,[0],[0],[0]],[[{"name":"5D_ZY_big_career_02","rect":{"x":193,"y":2,"width":86,"height":85},"offset":{"x":0,"y":-0.5},"originalSize":{"width":86,"height":86},"rotated":true,"capInsets":[0,0,0,0],"vertices":{"rawPosition":[],"indexes":[],"uv":[],"nuv":[],"minPos":{"x":0,"y":0,"z":0},"maxPos":{"x":0,"y":0,"z":0}},"packable":true,"pixelsToUnit":100,"pivot":{"x":0.5,"y":0.5},"meshType":0}],[0],0,[0],[0],[0]],[[{"name":"5D_ZY_big_career_03","rect":{"x":192,"y":193,"width":86,"height":85},"offset":{"x":0,"y":-0.5},"originalSize":{"width":86,"height":86},"rotated":false,"capInsets":[0,0,0,0],"vertices":{"rawPosition":[],"indexes":[],"uv":[],"nuv":[],"minPos":{"x":0,"y":0,"z":0},"maxPos":{"x":0,"y":0,"z":0}},"packable":true,"pixelsToUnit":100,"pivot":{"x":0.5,"y":0.5},"meshType":0}],[0],0,[0],[0],[0]],[[{"name":"5D_ZY_career_01","rect":{"x":130,"y":293,"width":54,"height":54},"offset":{"x":0,"y":0},"originalSize":{"width":56,"height":56},"rotated":false,"capInsets":[0,0,0,0],"vertices":{"rawPosition":[],"indexes":[],"uv":[],"nuv":[],"minPos":{"x":0,"y":0,"z":0},"maxPos":{"x":0,"y":0,"z":0}},"packable":true,"pixelsToUnit":100,"pivot":{"x":0.5,"y":0.5},"meshType":0}],[0],0,[0],[0],[0]],[[{"name":"5D_ZY_camp_07","rect":{"x":58,"y":355,"width":51,"height":51},"offset":{"x":-0.5,"y":0.5},"originalSize":{"width":56,"height":56},"rotated":false,"capInsets":[0,0,0,0],"vertices":{"rawPosition":[],"indexes":[],"uv":[],"nuv":[],"minPos":{"x":0,"y":0,"z":0},"maxPos":{"x":0,"y":0,"z":0}},"packable":true,"pixelsToUnit":100,"pivot":{"x":0.5,"y":0.5},"meshType":0}],[0],0,[0],[0],[0]],[[{"name":"5D_ZY_career_04","rect":{"x":340,"y":192,"width":54,"height":54},"offset":{"x":0,"y":0},"originalSize":{"width":56,"height":56},"rotated":false,"capInsets":[0,0,0,0],"vertices":{"rawPosition":[],"indexes":[],"uv":[],"nuv":[],"minPos":{"x":0,"y":0,"z":0},"maxPos":{"x":0,"y":0,"z":0}},"packable":true,"pixelsToUnit":100,"pivot":{"x":0.5,"y":0.5},"meshType":0}],[0],0,[0],[0],[0]],[[{"name":"5D_PZ_icon_y","rect":{"x":2,"y":180,"width":92,"height":82},"offset":{"x":1,"y":-1},"originalSize":{"width":100,"height":88},"rotated":false,"capInsets":[0,0,0,0],"vertices":{"rawPosition":[],"indexes":[],"uv":[],"nuv":[],"minPos":{"x":0,"y":0,"z":0},"maxPos":{"x":0,"y":0,"z":0}},"packable":true,"pixelsToUnit":100,"pivot":{"x":0.5,"y":0.5},"meshType":0}],[0],0,[0],[0],[0]],[[{"name":"5D_TY_stars_p","rect":{"x":66,"y":293,"width":60,"height":58},"offset":{"x":0,"y":0},"originalSize":{"width":60,"height":60},"rotated":false,"capInsets":[0,0,0,0],"vertices":{"rawPosition":[],"indexes":[],"uv":[],"nuv":[],"minPos":{"x":0,"y":0,"z":0},"maxPos":{"x":0,"y":0,"z":0}},"packable":true,"pixelsToUnit":100,"pivot":{"x":0.5,"y":0.5},"meshType":0}],[0],0,[0],[0],[0]],[[{"name":"5D_PZ_small_icon_p","rect":{"x":400,"y":2,"width":58,"height":27},"offset":{"x":0,"y":0.5},"originalSize":{"width":58,"height":28},"rotated":true,"capInsets":[0,0,0,0],"vertices":{"rawPosition":[],"indexes":[],"uv":[],"nuv":[],"minPos":{"x":0,"y":0,"z":0},"maxPos":{"x":0,"y":0,"z":0}},"packable":true,"pixelsToUnit":100,"pivot":{"x":0.5,"y":0.5},"meshType":0}],[0],0,[0],[0],[0]],[[{"name":"5D_ZY_career_03","rect":{"x":316,"y":250,"width":54,"height":54},"offset":{"x":0,"y":0},"originalSize":{"width":56,"height":56},"rotated":false,"capInsets":[0,0,0,0],"vertices":{"rawPosition":[],"indexes":[],"uv":[],"nuv":[],"minPos":{"x":0,"y":0,"z":0},"maxPos":{"x":0,"y":0,"z":0}},"packable":true,"pixelsToUnit":100,"pivot":{"x":0.5,"y":0.5},"meshType":0}],[0],0,[0],[0],[0]],[[{"name":"5D_ZY_camp_01","rect":{"x":344,"y":2,"width":52,"height":53},"offset":{"x":0,"y":0.5},"originalSize":{"width":56,"height":56},"rotated":false,"capInsets":[0,0,0,0],"vertices":{"rawPosition":[],"indexes":[],"uv":[],"nuv":[],"minPos":{"x":0,"y":0,"z":0},"maxPos":{"x":0,"y":0,"z":0}},"packable":true,"pixelsToUnit":100,"pivot":{"x":0.5,"y":0.5},"meshType":0}],[0],0,[0],[0],[0]],[[{"name":"5D_TY_lineup_g","rect":{"x":2,"y":385,"width":27,"height":43},"offset":{"x":-0.5,"y":-0.5},"originalSize":{"width":28,"height":44},"rotated":false,"capInsets":[0,0,0,0],"vertices":{"rawPosition":[],"indexes":[],"uv":[],"nuv":[],"minPos":{"x":0,"y":0,"z":0},"maxPos":{"x":0,"y":0,"z":0}},"packable":true,"pixelsToUnit":100,"pivot":{"x":0.5,"y":0.5},"meshType":0}],[0],0,[0],[0],[0]],[[{"name":"5D_TY_stars_b","rect":{"x":188,"y":282,"width":60,"height":58},"offset":{"x":0,"y":0},"originalSize":{"width":60,"height":60},"rotated":false,"capInsets":[0,0,0,0],"vertices":{"rawPosition":[],"indexes":[],"uv":[],"nuv":[],"minPos":{"x":0,"y":0,"z":0},"maxPos":{"x":0,"y":0,"z":0}},"packable":true,"pixelsToUnit":100,"pivot":{"x":0.5,"y":0.5},"meshType":0}],[0],0,[0],[0],[0]],[[{"name":"5D_TY_stars_pp","rect":{"x":252,"y":282,"width":60,"height":58},"offset":{"x":0,"y":0},"originalSize":{"width":60,"height":60},"rotated":false,"capInsets":[0,0,0,0],"vertices":{"rawPosition":[],"indexes":[],"uv":[],"nuv":[],"minPos":{"x":0,"y":0,"z":0},"maxPos":{"x":0,"y":0,"z":0}},"packable":true,"pixelsToUnit":100,"pivot":{"x":0.5,"y":0.5},"meshType":0}],[0],0,[0],[0],[0]],[[{"name":"5D_TY_lineup_y","rect":{"x":372,"y":308,"width":28,"height":43},"offset":{"x":0,"y":-0.5},"originalSize":{"width":28,"height":44},"rotated":false,"capInsets":[0,0,0,0],"vertices":{"rawPosition":[],"indexes":[],"uv":[],"nuv":[],"minPos":{"x":0,"y":0,"z":0},"maxPos":{"x":0,"y":0,"z":0}},"packable":true,"pixelsToUnit":100,"pivot":{"x":0.5,"y":0.5},"meshType":0}],[0],0,[0],[0],[0]],[[{"name":"5D_ZY_camp_08","rect":{"x":244,"y":344,"width":51,"height":51},"offset":{"x":-0.5,"y":0.5},"originalSize":{"width":56,"height":56},"rotated":false,"capInsets":[0,0,0,0],"vertices":{"rawPosition":[],"indexes":[],"uv":[],"nuv":[],"minPos":{"x":0,"y":0,"z":0},"maxPos":{"x":0,"y":0,"z":0}},"packable":true,"pixelsToUnit":100,"pivot":{"x":0.5,"y":0.5},"meshType":0}],[0],0,[0],[0],[0]],[[{"name":"5D_ZY_big_career_04","rect":{"x":98,"y":204,"width":86,"height":85},"offset":{"x":0,"y":-0.5},"originalSize":{"width":86,"height":86},"rotated":false,"capInsets":[0,0,0,0],"vertices":{"rawPosition":[],"indexes":[],"uv":[],"nuv":[],"minPos":{"x":0,"y":0,"z":0},"maxPos":{"x":0,"y":0,"z":0}},"packable":true,"pixelsToUnit":100,"pivot":{"x":0.5,"y":0.5},"meshType":0}],[0],0,[0],[0],[0]],[[{"name":"5D_ZY_career_02","rect":{"x":282,"y":192,"width":54,"height":54},"offset":{"x":0,"y":0},"originalSize":{"width":56,"height":56},"rotated":false,"capInsets":[0,0,0,0],"vertices":{"rawPosition":[],"indexes":[],"uv":[],"nuv":[],"minPos":{"x":0,"y":0,"z":0},"maxPos":{"x":0,"y":0,"z":0}},"packable":true,"pixelsToUnit":100,"pivot":{"x":0.5,"y":0.5},"meshType":0}],[0],0,[0],[0],[0]],[[{"name":"5D_PZ_small_icon_platinum","rect":{"x":361,"y":365,"width":58,"height":27},"offset":{"x":0,"y":0.5},"originalSize":{"width":58,"height":28},"rotated":false,"capInsets":[0,0,0,0],"vertices":{"rawPosition":[],"indexes":[],"uv":[],"nuv":[],"minPos":{"x":0,"y":0,"z":0},"maxPos":{"x":0,"y":0,"z":0}},"packable":true,"pixelsToUnit":100,"pivot":{"x":0.5,"y":0.5},"meshType":0}],[0],0,[0],[0],[0]],[[{"name":"5D_TY_stars_y","rect":{"x":282,"y":129,"width":59,"height":57},"offset":{"x":-0.5,"y":0.5},"originalSize":{"width":60,"height":60},"rotated":true,"capInsets":[0,0,0,0],"vertices":{"rawPosition":[],"indexes":[],"uv":[],"nuv":[],"minPos":{"x":0,"y":0,"z":0},"maxPos":{"x":0,"y":0,"z":0}},"packable":true,"pixelsToUnit":100,"pivot":{"x":0.5,"y":0.5},"meshType":0}],[0],0,[0],[0],[0]],[[{"name":"5D_TY_lineup_r","rect":{"x":299,"y":396,"width":27,"height":43},"offset":{"x":-0.5,"y":-0.5},"originalSize":{"width":28,"height":44},"rotated":false,"capInsets":[0,0,0,0],"vertices":{"rawPosition":[],"indexes":[],"uv":[],"nuv":[],"minPos":{"x":0,"y":0,"z":0},"maxPos":{"x":0,"y":0,"z":0}},"packable":true,"pixelsToUnit":100,"pivot":{"x":0.5,"y":0.5},"meshType":0}],[0],0,[0],[0],[0]],[[{"name":"5D_TY_lineup_b","rect":{"x":399,"y":126,"width":28,"height":44},"offset":{"x":0,"y":0},"originalSize":{"width":28,"height":44},"rotated":false,"capInsets":[0,0,0,0],"vertices":{"rawPosition":[],"indexes":[],"uv":[],"nuv":[],"minPos":{"x":0,"y":0,"z":0},"maxPos":{"x":0,"y":0,"z":0}},"packable":true,"pixelsToUnit":100,"pivot":{"x":0.5,"y":0.5},"meshType":0}],[0],0,[0],[0],[0]],[[{"name":"5D_PZ_icon_r","rect":{"x":105,"y":2,"width":98,"height":84},"offset":{"x":-1,"y":0},"originalSize":{"width":100,"height":88},"rotated":true,"capInsets":[0,0,0,0],"vertices":{"rawPosition":[],"indexes":[],"uv":[],"nuv":[],"minPos":{"x":0,"y":0,"z":0},"maxPos":{"x":0,"y":0,"z":0}},"packable":true,"pixelsToUnit":100,"pivot":{"x":0.5,"y":0.5},"meshType":0}],[0],0,[0],[0],[0]],[[{"name":"5D_ZY_camp_02","rect":{"x":343,"y":124,"width":52,"height":53},"offset":{"x":0,"y":0.5},"originalSize":{"width":56,"height":56},"rotated":false,"capInsets":[0,0,0,0],"vertices":{"rawPosition":[],"indexes":[],"uv":[],"nuv":[],"minPos":{"x":0,"y":0,"z":0},"maxPos":{"x":0,"y":0,"z":0}},"packable":true,"pixelsToUnit":100,"pivot":{"x":0.5,"y":0.5},"meshType":0}],[0],0,[0],[0],[0]],[[{"name":"5D_PZ_small_icon_b","rect":{"x":299,"y":365,"width":58,"height":27},"offset":{"x":0,"y":0.5},"originalSize":{"width":58,"height":28},"rotated":false,"capInsets":[0,0,0,0],"vertices":{"rawPosition":[],"indexes":[],"uv":[],"nuv":[],"minPos":{"x":0,"y":0,"z":0},"maxPos":{"x":0,"y":0,"z":0}},"packable":true,"pixelsToUnit":100,"pivot":{"x":0.5,"y":0.5},"meshType":0}],[0],0,[0],[0],[0]],[[{"name":"5D_PZ_icon_platinum","rect":{"x":2,"y":91,"width":97,"height":85},"offset":{"x":-0.5,"y":0.5},"originalSize":{"width":100,"height":88},"rotated":false,"capInsets":[0,0,0,0],"vertices":{"rawPosition":[],"indexes":[],"uv":[],"nuv":[],"minPos":{"x":0,"y":0,"z":0},"maxPos":{"x":0,"y":0,"z":0}},"packable":true,"pixelsToUnit":100,"pivot":{"x":0.5,"y":0.5},"meshType":0}],[0],0,[0],[0],[0]],[[{"name":"5D_ZY_career_all","rect":{"x":343,"y":66,"width":54,"height":54},"offset":{"x":0,"y":0},"originalSize":{"width":56,"height":56},"rotated":false,"capInsets":[0,0,0,0],"vertices":{"rawPosition":[],"indexes":[],"uv":[],"nuv":[],"minPos":{"x":0,"y":0,"z":0},"maxPos":{"x":0,"y":0,"z":0}},"packable":true,"pixelsToUnit":100,"pivot":{"x":0.5,"y":0.5},"meshType":0}],[0],0,[0],[0],[0]],[[{"name":"5D_TY_stars_r","rect":{"x":282,"y":2,"width":60,"height":58},"offset":{"x":0,"y":0},"originalSize":{"width":60,"height":60},"rotated":true,"capInsets":[0,0,0,0],"vertices":{"rawPosition":[],"indexes":[],"uv":[],"nuv":[],"minPos":{"x":0,"y":0,"z":0},"maxPos":{"x":0,"y":0,"z":0}},"packable":true,"pixelsToUnit":100,"pivot":{"x":0.5,"y":0.5},"meshType":0}],[0],0,[0],[0],[0]],[[{"name":"5D_ZY_camp_05","rect":{"x":188,"y":344,"width":52,"height":53},"offset":{"x":0,"y":0.5},"originalSize":{"width":56,"height":56},"rotated":false,"capInsets":[0,0,0,0],"vertices":{"rawPosition":[],"indexes":[],"uv":[],"nuv":[],"minPos":{"x":0,"y":0,"z":0},"maxPos":{"x":0,"y":0,"z":0}},"packable":true,"pixelsToUnit":100,"pivot":{"x":0.5,"y":0.5},"meshType":0}],[0],0,[0],[0],[0]],[[{"name":"5D_TY_stars_w","rect":{"x":282,"y":66,"width":59,"height":57},"offset":{"x":-0.5,"y":0.5},"originalSize":{"width":60,"height":60},"rotated":true,"capInsets":[0,0,0,0],"vertices":{"rawPosition":[],"indexes":[],"uv":[],"nuv":[],"minPos":{"x":0,"y":0,"z":0},"maxPos":{"x":0,"y":0,"z":0}},"packable":true,"pixelsToUnit":100,"pivot":{"x":0.5,"y":0.5},"meshType":0}],[0],0,[0],[0],[0]],[[{"name":"5D_PZ_small_icon_y","rect":{"x":401,"y":64,"width":58,"height":27},"offset":{"x":0,"y":0.5},"originalSize":{"width":58,"height":28},"rotated":true,"capInsets":[0,0,0,0],"vertices":{"rawPosition":[],"indexes":[],"uv":[],"nuv":[],"minPos":{"x":0,"y":0,"z":0},"maxPos":{"x":0,"y":0,"z":0}},"packable":true,"pixelsToUnit":100,"pivot":{"x":0.5,"y":0.5},"meshType":0}],[0],0,[0],[0],[0]]]]
