[1,0,0,[["cc.JsonAsset",["_name","json"],1]],[[0,0,1,3]],[[0,"NPYangChengGongShi_1_30404",{"Datas":[{"_id":1,"ID":1,"Formula":1,"AttrID":[0,1,2,3],"AttrValue":[4182,610,113,113],"Params":[100,0.1,0.252]},{"_id":2,"ID":2,"Formula":2,"AttrID":[0,1,2,3],"AttrValue":[4182,610,113,113],"Params":[0.1,0.108,0]},{"_id":10101,"ID":10101,"Formula":1,"AttrID":[0,1,2,3],"AttrValue":[642,94,17,17],"Params":[100,0.1,0.144]},{"_id":10102,"ID":10102,"Formula":1,"AttrID":[0,1,2,3],"AttrValue":[1171,171,32,32],"Params":[100,0.1,0.144]},{"_id":10103,"ID":10103,"Formula":1,"AttrID":[0,1,2,3],"AttrValue":[2133,311,58,58],"Params":[100,0.1,0.144]},{"_id":10104,"ID":10104,"Formula":1,"AttrID":[0,1,2,3],"AttrValue":[2880,420,78,78],"Params":[100,0.1,0.144]},{"_id":10105,"ID":10105,"Formula":1,"AttrID":[0,1,2,3],"AttrValue":[3888,567,105,105],"Params":[100,0.1,0.144]},{"_id":10106,"ID":10106,"Formula":1,"AttrID":[0,1,2,3],"AttrValue":[5249,765,142,142],"Params":[100,0.1,0.144]},{"_id":10201,"ID":10201,"Formula":1,"AttrID":[0,1,2,3],"AttrValue":[739,89,17,17],"Params":[100,0.1,0.144]},{"_id":10202,"ID":10202,"Formula":1,"AttrID":[0,1,2,3],"AttrValue":[1346,162,30,30],"Params":[100,0.1,0.144]},{"_id":10203,"ID":10203,"Formula":1,"AttrID":[0,1,2,3],"AttrValue":[2453,296,55,55],"Params":[100,0.1,0.144]},{"_id":10204,"ID":10204,"Formula":1,"AttrID":[0,1,2,3],"AttrValue":[3312,399,74,74],"Params":[100,0.1,0.144]},{"_id":10205,"ID":10205,"Formula":1,"AttrID":[0,1,2,3],"AttrValue":[4471,539,100,100],"Params":[100,0.1,0.144]},{"_id":10206,"ID":10206,"Formula":1,"AttrID":[0,1,2,3],"AttrValue":[6036,727,135,135],"Params":[100,0.1,0.144]},{"_id":10301,"ID":10301,"Formula":1,"AttrID":[0,1,2,3],"AttrValue":[642,66,21,21],"Params":[100,0.1,0.144]},{"_id":10302,"ID":10302,"Formula":1,"AttrID":[0,1,2,3],"AttrValue":[1171,119,38,38],"Params":[100,0.1,0.144]},{"_id":10303,"ID":10303,"Formula":1,"AttrID":[0,1,2,3],"AttrValue":[2133,218,69,69],"Params":[100,0.1,0.144]},{"_id":10304,"ID":10304,"Formula":1,"AttrID":[0,1,2,3],"AttrValue":[2880,294,94,94],"Params":[100,0.1,0.144]},{"_id":10305,"ID":10305,"Formula":1,"AttrID":[0,1,2,3],"AttrValue":[3888,397,126,126],"Params":[100,0.1,0.144]},{"_id":10306,"ID":10306,"Formula":1,"AttrID":[0,1,2,3],"AttrValue":[5249,536,171,171],"Params":[100,0.1,0.144]},{"_id":10401,"ID":10401,"Formula":1,"AttrID":[0,1,2,3],"AttrValue":[739,80,17,17],"Params":[100,0.1,0.144]},{"_id":10402,"ID":10402,"Formula":1,"AttrID":[0,1,2,3],"AttrValue":[1346,145,32,32],"Params":[100,0.1,0.144]},{"_id":10403,"ID":10403,"Formula":1,"AttrID":[0,1,2,3],"AttrValue":[2453,264,58,58],"Params":[100,0.1,0.144]},{"_id":10404,"ID":10404,"Formula":1,"AttrID":[0,1,2,3],"AttrValue":[3312,357,78,78],"Params":[100,0.1,0.144]},{"_id":10405,"ID":10405,"Formula":1,"AttrID":[0,1,2,3],"AttrValue":[4471,482,105,105],"Params":[100,0.1,0.144]},{"_id":10406,"ID":10406,"Formula":1,"AttrID":[0,1,2,3],"AttrValue":[6036,651,142,142],"Params":[100,0.1,0.144]},{"_id":20101,"ID":20101,"Formula":1,"AttrID":[0,1,2,3],"AttrValue":[642,94,17,17],"Params":[100,0.1,0.216]},{"_id":20102,"ID":20102,"Formula":1,"AttrID":[0,1,2,3],"AttrValue":[1171,171,32,32],"Params":[100,0.1,0.216]},{"_id":20103,"ID":20103,"Formula":1,"AttrID":[0,1,2,3],"AttrValue":[2133,311,58,58],"Params":[100,0.1,0.216]},{"_id":20104,"ID":20104,"Formula":1,"AttrID":[0,1,2,3],"AttrValue":[2880,420,78,78],"Params":[100,0.1,0.216]},{"_id":20105,"ID":20105,"Formula":1,"AttrID":[0,1,2,3],"AttrValue":[3888,567,105,105],"Params":[100,0.1,0.216]},{"_id":20106,"ID":20106,"Formula":1,"AttrID":[0,1,2,3],"AttrValue":[5249,765,142,142],"Params":[100,0.1,0.216]},{"_id":20201,"ID":20201,"Formula":1,"AttrID":[0,1,2,3],"AttrValue":[739,89,17,17],"Params":[100,0.1,0.216]},{"_id":20202,"ID":20202,"Formula":1,"AttrID":[0,1,2,3],"AttrValue":[1346,162,30,30],"Params":[100,0.1,0.216]},{"_id":20203,"ID":20203,"Formula":1,"AttrID":[0,1,2,3],"AttrValue":[2453,296,55,55],"Params":[100,0.1,0.216]},{"_id":20204,"ID":20204,"Formula":1,"AttrID":[0,1,2,3],"AttrValue":[3312,399,74,74],"Params":[100,0.1,0.216]},{"_id":20205,"ID":20205,"Formula":1,"AttrID":[0,1,2,3],"AttrValue":[4471,539,100,100],"Params":[100,0.1,0.216]},{"_id":20206,"ID":20206,"Formula":1,"AttrID":[0,1,2,3],"AttrValue":[6036,727,135,135],"Params":[100,0.1,0.216]},{"_id":20301,"ID":20301,"Formula":1,"AttrID":[0,1,2,3],"AttrValue":[642,66,21,21],"Params":[100,0.1,0.216]},{"_id":20302,"ID":20302,"Formula":1,"AttrID":[0,1,2,3],"AttrValue":[1171,119,38,38],"Params":[100,0.1,0.216]},{"_id":20303,"ID":20303,"Formula":1,"AttrID":[0,1,2,3],"AttrValue":[2133,218,69,69],"Params":[100,0.1,0.216]},{"_id":20304,"ID":20304,"Formula":1,"AttrID":[0,1,2,3],"AttrValue":[2880,294,94,94],"Params":[100,0.1,0.216]},{"_id":20305,"ID":20305,"Formula":1,"AttrID":[0,1,2,3],"AttrValue":[3888,397,126,126],"Params":[100,0.1,0.216]},{"_id":20306,"ID":20306,"Formula":1,"AttrID":[0,1,2,3],"AttrValue":[5249,536,171,171],"Params":[100,0.1,0.216]},{"_id":20401,"ID":20401,"Formula":1,"AttrID":[0,1,2,3],"AttrValue":[739,80,17,17],"Params":[100,0.1,0.216]},{"_id":20402,"ID":20402,"Formula":1,"AttrID":[0,1,2,3],"AttrValue":[1346,145,32,32],"Params":[100,0.1,0.216]},{"_id":20403,"ID":20403,"Formula":1,"AttrID":[0,1,2,3],"AttrValue":[2453,264,58,58],"Params":[100,0.1,0.216]},{"_id":20404,"ID":20404,"Formula":1,"AttrID":[0,1,2,3],"AttrValue":[3312,357,78,78],"Params":[100,0.1,0.216]},{"_id":20405,"ID":20405,"Formula":1,"AttrID":[0,1,2,3],"AttrValue":[4471,482,105,105],"Params":[100,0.1,0.216]},{"_id":20406,"ID":20406,"Formula":1,"AttrID":[0,1,2,3],"AttrValue":[6036,651,142,142],"Params":[100,0.1,0.216]},{"_id":30101,"ID":30101,"Formula":3,"AttrID":[0,0,0,0],"AttrValue":[2880,0,0,0],"Params":[0.005,0.1,0]},{"_id":30102,"ID":30102,"Formula":3,"AttrID":[1,0,0,0],"AttrValue":[420,0,0,0],"Params":[0.005,0.1,0]},{"_id":30103,"ID":30103,"Formula":3,"AttrID":[2,3,0,0],"AttrValue":[78,78,0,0],"Params":[0.005,0.1,0]},{"_id":30104,"ID":30104,"Formula":3,"AttrID":[27,0,0,0],"AttrValue":[2000,0,0,0],"Params":[0.005,0,0]},{"_id":30201,"ID":30201,"Formula":3,"AttrID":[0,0,0,0],"AttrValue":[3312,0,0,0],"Params":[0.005,0.1,0]},{"_id":30202,"ID":30202,"Formula":3,"AttrID":[1,0,0,0],"AttrValue":[399,0,0,0],"Params":[0.005,0.1,0]},{"_id":30203,"ID":30203,"Formula":3,"AttrID":[2,3,0,0],"AttrValue":[74,74,0,0],"Params":[0.005,0.1,0]},{"_id":30204,"ID":30204,"Formula":3,"AttrID":[27,0,0,0],"AttrValue":[2000,0,0,0],"Params":[0.005,0,0]},{"_id":30301,"ID":30301,"Formula":3,"AttrID":[0,0,0,0],"AttrValue":[2880,0,0,0],"Params":[0.005,0.1,0]},{"_id":30302,"ID":30302,"Formula":3,"AttrID":[1,0,0,0],"AttrValue":[294,0,0,0],"Params":[0.005,0.1,0]},{"_id":30303,"ID":30303,"Formula":3,"AttrID":[2,3,0,0],"AttrValue":[94,94,0,0],"Params":[0.005,0.1,0]},{"_id":30304,"ID":30304,"Formula":3,"AttrID":[27,0,0,0],"AttrValue":[2000,0,0,0],"Params":[0.005,0,0]},{"_id":30401,"ID":30401,"Formula":3,"AttrID":[0,0,0,0],"AttrValue":[3312,0,0,0],"Params":[0.005,0.1,0]},{"_id":30402,"ID":30402,"Formula":3,"AttrID":[1,0,0,0],"AttrValue":[357,0,0,0],"Params":[0.005,0.1,0]},{"_id":30403,"ID":30403,"Formula":3,"AttrID":[2,3,0,0],"AttrValue":[78,78,0,0],"Params":[0.005,0.1,0]},{"_id":30404,"ID":30404,"Formula":3,"AttrID":[27,0,0,0],"AttrValue":[2000,0,0,0],"Params":[0.005,0,0]}]}]],0,0,[],[],[]]
