[1,0,0,[["cc.JsonAsset",["_name","json"],1]],[[0,0,1,3]],[[0,"ZhuanShuZhuangBei_3101_6170",{"Datas":[{"_id":3101,"ExclusiveEquipId":3101,"ExclusiveEquipName":280000301,"ExclusiveEquipIcon":"ZSZB_lan_01","TeshuShuXingIcon":"","Quality":3,"DangCi":3,"Property":1,"ExclusiveEquipMiaoShu":280001301,"MaxUPgeade":20,"QiangHua":3,"MaxStar":0,"ExclusiveEquipStarAttr":1000000,"TeshuShuXingID":0,"TeshuJiNengFanYiID":0,"ExclusiveNinJas":0,"WNType":0,"WNID":0,"ExchangeID":0,"ExchangeCostType":0,"ExchangeCostID":0,"ExchangeCostCount":0,"JiBanJiNengIcon":[""],"TeshuJiNengStar":[0],"TeshuJiNengID":[0],"CostType":[2,0,0,0],"CostID":[6056,0,0,0],"CostNum":[20,0,0,0]},{"_id":3102,"ExclusiveEquipId":3102,"ExclusiveEquipName":280000302,"ExclusiveEquipIcon":"ZSZB_lan_02","TeshuShuXingIcon":"","Quality":3,"DangCi":3,"Property":1,"ExclusiveEquipMiaoShu":280001302,"MaxUPgeade":20,"QiangHua":1,"MaxStar":0,"ExclusiveEquipStarAttr":1000000,"TeshuShuXingID":0,"TeshuJiNengFanYiID":0,"ExclusiveNinJas":0,"WNType":0,"WNID":0,"ExchangeID":0,"ExchangeCostType":0,"ExchangeCostID":0,"ExchangeCostCount":0,"JiBanJiNengIcon":[""],"TeshuJiNengStar":[0],"TeshuJiNengID":[0],"CostType":[2,0,0,0],"CostID":[6056,0,0,0],"CostNum":[20,0,0,0]},{"_id":3103,"ExclusiveEquipId":3103,"ExclusiveEquipName":280000303,"ExclusiveEquipIcon":"ZSZB_lan_03","TeshuShuXingIcon":"","Quality":3,"DangCi":3,"Property":1,"ExclusiveEquipMiaoShu":280001303,"MaxUPgeade":20,"QiangHua":3,"MaxStar":0,"ExclusiveEquipStarAttr":1000000,"TeshuShuXingID":0,"TeshuJiNengFanYiID":0,"ExclusiveNinJas":0,"WNType":0,"WNID":0,"ExchangeID":0,"ExchangeCostType":0,"ExchangeCostID":0,"ExchangeCostCount":0,"JiBanJiNengIcon":[""],"TeshuJiNengStar":[0],"TeshuJiNengID":[0],"CostType":[2,0,0,0],"CostID":[6056,0,0,0],"CostNum":[20,0,0,0]},{"_id":3104,"ExclusiveEquipId":3104,"ExclusiveEquipName":280000304,"ExclusiveEquipIcon":"ZSZB_lan_04","TeshuShuXingIcon":"","Quality":3,"DangCi":3,"Property":1,"ExclusiveEquipMiaoShu":280001304,"MaxUPgeade":20,"QiangHua":1,"MaxStar":0,"ExclusiveEquipStarAttr":1000000,"TeshuShuXingID":0,"TeshuJiNengFanYiID":0,"ExclusiveNinJas":0,"WNType":0,"WNID":0,"ExchangeID":0,"ExchangeCostType":0,"ExchangeCostID":0,"ExchangeCostCount":0,"JiBanJiNengIcon":[""],"TeshuJiNengStar":[0],"TeshuJiNengID":[0],"CostType":[2,0,0,0],"CostID":[6056,0,0,0],"CostNum":[20,0,0,0]},{"_id":3105,"ExclusiveEquipId":3105,"ExclusiveEquipName":280000305,"ExclusiveEquipIcon":"ZSZB_lan_05","TeshuShuXingIcon":"","Quality":3,"DangCi":3,"Property":1,"ExclusiveEquipMiaoShu":280001305,"MaxUPgeade":20,"QiangHua":3,"MaxStar":0,"ExclusiveEquipStarAttr":1000000,"TeshuShuXingID":0,"TeshuJiNengFanYiID":0,"ExclusiveNinJas":0,"WNType":0,"WNID":0,"ExchangeID":0,"ExchangeCostType":0,"ExchangeCostID":0,"ExchangeCostCount":0,"JiBanJiNengIcon":[""],"TeshuJiNengStar":[0],"TeshuJiNengID":[0],"CostType":[2,0,0,0],"CostID":[6056,0,0,0],"CostNum":[20,0,0,0]},{"_id":3106,"ExclusiveEquipId":3106,"ExclusiveEquipName":280000306,"ExclusiveEquipIcon":"ZSZB_lan_06","TeshuShuXingIcon":"","Quality":3,"DangCi":3,"Property":1,"ExclusiveEquipMiaoShu":280001306,"MaxUPgeade":20,"QiangHua":1,"MaxStar":0,"ExclusiveEquipStarAttr":1000000,"TeshuShuXingID":0,"TeshuJiNengFanYiID":0,"ExclusiveNinJas":0,"WNType":0,"WNID":0,"ExchangeID":0,"ExchangeCostType":0,"ExchangeCostID":0,"ExchangeCostCount":0,"JiBanJiNengIcon":[""],"TeshuJiNengStar":[0],"TeshuJiNengID":[0],"CostType":[2,0,0,0],"CostID":[6056,0,0,0],"CostNum":[20,0,0,0]},{"_id":3107,"ExclusiveEquipId":3107,"ExclusiveEquipName":280000307,"ExclusiveEquipIcon":"ZSZB_lan_07","TeshuShuXingIcon":"","Quality":3,"DangCi":3,"Property":1,"ExclusiveEquipMiaoShu":280001307,"MaxUPgeade":20,"QiangHua":2,"MaxStar":0,"ExclusiveEquipStarAttr":1000000,"TeshuShuXingID":0,"TeshuJiNengFanYiID":0,"ExclusiveNinJas":0,"WNType":0,"WNID":0,"ExchangeID":0,"ExchangeCostType":0,"ExchangeCostID":0,"ExchangeCostCount":0,"JiBanJiNengIcon":[""],"TeshuJiNengStar":[0],"TeshuJiNengID":[0],"CostType":[2,0,0,0],"CostID":[6056,0,0,0],"CostNum":[20,0,0,0]},{"_id":3108,"ExclusiveEquipId":3108,"ExclusiveEquipName":280000308,"ExclusiveEquipIcon":"ZSZB_lan_08","TeshuShuXingIcon":"","Quality":3,"DangCi":3,"Property":1,"ExclusiveEquipMiaoShu":280001308,"MaxUPgeade":20,"QiangHua":3,"MaxStar":0,"ExclusiveEquipStarAttr":1000000,"TeshuShuXingID":0,"TeshuJiNengFanYiID":0,"ExclusiveNinJas":0,"WNType":0,"WNID":0,"ExchangeID":0,"ExchangeCostType":0,"ExchangeCostID":0,"ExchangeCostCount":0,"JiBanJiNengIcon":[""],"TeshuJiNengStar":[0],"TeshuJiNengID":[0],"CostType":[2,0,0,0],"CostID":[6056,0,0,0],"CostNum":[20,0,0,0]},{"_id":3109,"ExclusiveEquipId":3109,"ExclusiveEquipName":280000309,"ExclusiveEquipIcon":"ZSZB_lan_09","TeshuShuXingIcon":"","Quality":3,"DangCi":3,"Property":1,"ExclusiveEquipMiaoShu":280001309,"MaxUPgeade":20,"QiangHua":1,"MaxStar":0,"ExclusiveEquipStarAttr":1000000,"TeshuShuXingID":0,"TeshuJiNengFanYiID":0,"ExclusiveNinJas":0,"WNType":0,"WNID":0,"ExchangeID":0,"ExchangeCostType":0,"ExchangeCostID":0,"ExchangeCostCount":0,"JiBanJiNengIcon":[""],"TeshuJiNengStar":[0],"TeshuJiNengID":[0],"CostType":[2,0,0,0],"CostID":[6056,0,0,0],"CostNum":[20,0,0,0]},{"_id":3110,"ExclusiveEquipId":3110,"ExclusiveEquipName":280000310,"ExclusiveEquipIcon":"ZSZB_lan_10","TeshuShuXingIcon":"","Quality":3,"DangCi":3,"Property":1,"ExclusiveEquipMiaoShu":280001310,"MaxUPgeade":20,"QiangHua":2,"MaxStar":0,"ExclusiveEquipStarAttr":1000000,"TeshuShuXingID":0,"TeshuJiNengFanYiID":0,"ExclusiveNinJas":0,"WNType":0,"WNID":0,"ExchangeID":0,"ExchangeCostType":0,"ExchangeCostID":0,"ExchangeCostCount":0,"JiBanJiNengIcon":[""],"TeshuJiNengStar":[0],"TeshuJiNengID":[0],"CostType":[2,0,0,0],"CostID":[6056,0,0,0],"CostNum":[20,0,0,0]},{"_id":3111,"ExclusiveEquipId":3111,"ExclusiveEquipName":280000311,"ExclusiveEquipIcon":"ZSZB_lan_11","TeshuShuXingIcon":"","Quality":3,"DangCi":3,"Property":1,"ExclusiveEquipMiaoShu":280001311,"MaxUPgeade":20,"QiangHua":2,"MaxStar":0,"ExclusiveEquipStarAttr":1000000,"TeshuShuXingID":0,"TeshuJiNengFanYiID":0,"ExclusiveNinJas":0,"WNType":0,"WNID":0,"ExchangeID":0,"ExchangeCostType":0,"ExchangeCostID":0,"ExchangeCostCount":0,"JiBanJiNengIcon":[""],"TeshuJiNengStar":[0],"TeshuJiNengID":[0],"CostType":[2,0,0,0],"CostID":[6056,0,0,0],"CostNum":[20,0,0,0]},{"_id":3112,"ExclusiveEquipId":3112,"ExclusiveEquipName":280000312,"ExclusiveEquipIcon":"ZSZB_lan_12","TeshuShuXingIcon":"","Quality":3,"DangCi":3,"Property":1,"ExclusiveEquipMiaoShu":280001312,"MaxUPgeade":20,"QiangHua":3,"MaxStar":0,"ExclusiveEquipStarAttr":1000000,"TeshuShuXingID":0,"TeshuJiNengFanYiID":0,"ExclusiveNinJas":0,"WNType":0,"WNID":0,"ExchangeID":0,"ExchangeCostType":0,"ExchangeCostID":0,"ExchangeCostCount":0,"JiBanJiNengIcon":[""],"TeshuJiNengStar":[0],"TeshuJiNengID":[0],"CostType":[2,0,0,0],"CostID":[6056,0,0,0],"CostNum":[20,0,0,0]},{"_id":3113,"ExclusiveEquipId":3113,"ExclusiveEquipName":280000313,"ExclusiveEquipIcon":"ZSZB_lan_13","TeshuShuXingIcon":"","Quality":3,"DangCi":3,"Property":1,"ExclusiveEquipMiaoShu":280001313,"MaxUPgeade":20,"QiangHua":2,"MaxStar":0,"ExclusiveEquipStarAttr":1000000,"TeshuShuXingID":0,"TeshuJiNengFanYiID":0,"ExclusiveNinJas":0,"WNType":0,"WNID":0,"ExchangeID":0,"ExchangeCostType":0,"ExchangeCostID":0,"ExchangeCostCount":0,"JiBanJiNengIcon":[""],"TeshuJiNengStar":[0],"TeshuJiNengID":[0],"CostType":[2,0,0,0],"CostID":[6056,0,0,0],"CostNum":[20,0,0,0]},{"_id":4101,"ExclusiveEquipId":4101,"ExclusiveEquipName":280000401,"ExclusiveEquipIcon":"ZSZB_zi_01","TeshuShuXingIcon":"","Quality":5,"DangCi":4,"Property":1,"ExclusiveEquipMiaoShu":280001301,"MaxUPgeade":30,"QiangHua":13,"MaxStar":1,"ExclusiveEquipStarAttr":2000000,"TeshuShuXingID":0,"TeshuJiNengFanYiID":0,"ExclusiveNinJas":0,"WNType":0,"WNID":0,"ExchangeID":0,"ExchangeCostType":0,"ExchangeCostID":0,"ExchangeCostCount":0,"JiBanJiNengIcon":[""],"TeshuJiNengStar":[0],"TeshuJiNengID":[0],"CostType":[2,2,0,0],"CostID":[6056,6057,0,0],"CostNum":[35,1,0,0]},{"_id":4102,"ExclusiveEquipId":4102,"ExclusiveEquipName":280000402,"ExclusiveEquipIcon":"ZSZB_zi_02","TeshuShuXingIcon":"","Quality":5,"DangCi":4,"Property":1,"ExclusiveEquipMiaoShu":280001302,"MaxUPgeade":30,"QiangHua":11,"MaxStar":1,"ExclusiveEquipStarAttr":2000000,"TeshuShuXingID":0,"TeshuJiNengFanYiID":0,"ExclusiveNinJas":0,"WNType":0,"WNID":0,"ExchangeID":0,"ExchangeCostType":0,"ExchangeCostID":0,"ExchangeCostCount":0,"JiBanJiNengIcon":[""],"TeshuJiNengStar":[0],"TeshuJiNengID":[0],"CostType":[2,2,0,0],"CostID":[6056,6057,0,0],"CostNum":[35,1,0,0]},{"_id":4103,"ExclusiveEquipId":4103,"ExclusiveEquipName":280000403,"ExclusiveEquipIcon":"ZSZB_zi_03","TeshuShuXingIcon":"","Quality":5,"DangCi":4,"Property":1,"ExclusiveEquipMiaoShu":280001303,"MaxUPgeade":30,"QiangHua":13,"MaxStar":1,"ExclusiveEquipStarAttr":2000000,"TeshuShuXingID":0,"TeshuJiNengFanYiID":0,"ExclusiveNinJas":0,"WNType":0,"WNID":0,"ExchangeID":0,"ExchangeCostType":0,"ExchangeCostID":0,"ExchangeCostCount":0,"JiBanJiNengIcon":[""],"TeshuJiNengStar":[0],"TeshuJiNengID":[0],"CostType":[2,2,0,0],"CostID":[6056,6057,0,0],"CostNum":[35,1,0,0]},{"_id":4104,"ExclusiveEquipId":4104,"ExclusiveEquipName":280000404,"ExclusiveEquipIcon":"ZSZB_zi_04","TeshuShuXingIcon":"","Quality":5,"DangCi":4,"Property":1,"ExclusiveEquipMiaoShu":280001304,"MaxUPgeade":30,"QiangHua":11,"MaxStar":1,"ExclusiveEquipStarAttr":2000000,"TeshuShuXingID":0,"TeshuJiNengFanYiID":0,"ExclusiveNinJas":0,"WNType":0,"WNID":0,"ExchangeID":0,"ExchangeCostType":0,"ExchangeCostID":0,"ExchangeCostCount":0,"JiBanJiNengIcon":[""],"TeshuJiNengStar":[0],"TeshuJiNengID":[0],"CostType":[2,2,0,0],"CostID":[6056,6057,0,0],"CostNum":[35,1,0,0]},{"_id":4105,"ExclusiveEquipId":4105,"ExclusiveEquipName":280000405,"ExclusiveEquipIcon":"ZSZB_zi_05","TeshuShuXingIcon":"","Quality":5,"DangCi":4,"Property":1,"ExclusiveEquipMiaoShu":280001305,"MaxUPgeade":30,"QiangHua":13,"MaxStar":1,"ExclusiveEquipStarAttr":2000000,"TeshuShuXingID":0,"TeshuJiNengFanYiID":0,"ExclusiveNinJas":0,"WNType":0,"WNID":0,"ExchangeID":0,"ExchangeCostType":0,"ExchangeCostID":0,"ExchangeCostCount":0,"JiBanJiNengIcon":[""],"TeshuJiNengStar":[0],"TeshuJiNengID":[0],"CostType":[2,2,0,0],"CostID":[6056,6057,0,0],"CostNum":[35,1,0,0]},{"_id":4106,"ExclusiveEquipId":4106,"ExclusiveEquipName":280000406,"ExclusiveEquipIcon":"ZSZB_zi_06","TeshuShuXingIcon":"","Quality":5,"DangCi":4,"Property":1,"ExclusiveEquipMiaoShu":280001306,"MaxUPgeade":30,"QiangHua":11,"MaxStar":1,"ExclusiveEquipStarAttr":2000000,"TeshuShuXingID":0,"TeshuJiNengFanYiID":0,"ExclusiveNinJas":0,"WNType":0,"WNID":0,"ExchangeID":0,"ExchangeCostType":0,"ExchangeCostID":0,"ExchangeCostCount":0,"JiBanJiNengIcon":[""],"TeshuJiNengStar":[0],"TeshuJiNengID":[0],"CostType":[2,2,0,0],"CostID":[6056,6057,0,0],"CostNum":[35,1,0,0]},{"_id":4107,"ExclusiveEquipId":4107,"ExclusiveEquipName":280000407,"ExclusiveEquipIcon":"ZSZB_zi_07","TeshuShuXingIcon":"","Quality":5,"DangCi":4,"Property":1,"ExclusiveEquipMiaoShu":280001307,"MaxUPgeade":30,"QiangHua":12,"MaxStar":1,"ExclusiveEquipStarAttr":2000000,"TeshuShuXingID":0,"TeshuJiNengFanYiID":0,"ExclusiveNinJas":0,"WNType":0,"WNID":0,"ExchangeID":0,"ExchangeCostType":0,"ExchangeCostID":0,"ExchangeCostCount":0,"JiBanJiNengIcon":[""],"TeshuJiNengStar":[0],"TeshuJiNengID":[0],"CostType":[2,2,0,0],"CostID":[6056,6057,0,0],"CostNum":[35,1,0,0]},{"_id":4108,"ExclusiveEquipId":4108,"ExclusiveEquipName":280000408,"ExclusiveEquipIcon":"ZSZB_zi_08","TeshuShuXingIcon":"","Quality":5,"DangCi":4,"Property":1,"ExclusiveEquipMiaoShu":280001308,"MaxUPgeade":30,"QiangHua":13,"MaxStar":1,"ExclusiveEquipStarAttr":2000000,"TeshuShuXingID":0,"TeshuJiNengFanYiID":0,"ExclusiveNinJas":0,"WNType":0,"WNID":0,"ExchangeID":0,"ExchangeCostType":0,"ExchangeCostID":0,"ExchangeCostCount":0,"JiBanJiNengIcon":[""],"TeshuJiNengStar":[0],"TeshuJiNengID":[0],"CostType":[2,2,0,0],"CostID":[6056,6057,0,0],"CostNum":[35,1,0,0]},{"_id":4109,"ExclusiveEquipId":4109,"ExclusiveEquipName":280000409,"ExclusiveEquipIcon":"ZSZB_zi_09","TeshuShuXingIcon":"","Quality":5,"DangCi":4,"Property":1,"ExclusiveEquipMiaoShu":280001309,"MaxUPgeade":30,"QiangHua":11,"MaxStar":1,"ExclusiveEquipStarAttr":2000000,"TeshuShuXingID":0,"TeshuJiNengFanYiID":0,"ExclusiveNinJas":0,"WNType":0,"WNID":0,"ExchangeID":0,"ExchangeCostType":0,"ExchangeCostID":0,"ExchangeCostCount":0,"JiBanJiNengIcon":[""],"TeshuJiNengStar":[0],"TeshuJiNengID":[0],"CostType":[2,2,0,0],"CostID":[6056,6057,0,0],"CostNum":[35,1,0,0]},{"_id":4110,"ExclusiveEquipId":4110,"ExclusiveEquipName":280000410,"ExclusiveEquipIcon":"ZSZB_zi_10","TeshuShuXingIcon":"","Quality":5,"DangCi":4,"Property":1,"ExclusiveEquipMiaoShu":280001310,"MaxUPgeade":30,"QiangHua":12,"MaxStar":1,"ExclusiveEquipStarAttr":2000000,"TeshuShuXingID":0,"TeshuJiNengFanYiID":0,"ExclusiveNinJas":0,"WNType":0,"WNID":0,"ExchangeID":0,"ExchangeCostType":0,"ExchangeCostID":0,"ExchangeCostCount":0,"JiBanJiNengIcon":[""],"TeshuJiNengStar":[0],"TeshuJiNengID":[0],"CostType":[2,2,0,0],"CostID":[6056,6057,0,0],"CostNum":[35,1,0,0]},{"_id":4111,"ExclusiveEquipId":4111,"ExclusiveEquipName":280000411,"ExclusiveEquipIcon":"ZSZB_zi_11","TeshuShuXingIcon":"","Quality":5,"DangCi":4,"Property":1,"ExclusiveEquipMiaoShu":280001311,"MaxUPgeade":30,"QiangHua":12,"MaxStar":1,"ExclusiveEquipStarAttr":2000000,"TeshuShuXingID":0,"TeshuJiNengFanYiID":0,"ExclusiveNinJas":0,"WNType":0,"WNID":0,"ExchangeID":0,"ExchangeCostType":0,"ExchangeCostID":0,"ExchangeCostCount":0,"JiBanJiNengIcon":[""],"TeshuJiNengStar":[0],"TeshuJiNengID":[0],"CostType":[2,2,0,0],"CostID":[6056,6057,0,0],"CostNum":[35,1,0,0]},{"_id":4112,"ExclusiveEquipId":4112,"ExclusiveEquipName":280000412,"ExclusiveEquipIcon":"ZSZB_zi_12","TeshuShuXingIcon":"","Quality":5,"DangCi":4,"Property":1,"ExclusiveEquipMiaoShu":280001312,"MaxUPgeade":30,"QiangHua":13,"MaxStar":1,"ExclusiveEquipStarAttr":2000000,"TeshuShuXingID":0,"TeshuJiNengFanYiID":0,"ExclusiveNinJas":0,"WNType":0,"WNID":0,"ExchangeID":0,"ExchangeCostType":0,"ExchangeCostID":0,"ExchangeCostCount":0,"JiBanJiNengIcon":[""],"TeshuJiNengStar":[0],"TeshuJiNengID":[0],"CostType":[2,2,0,0],"CostID":[6056,6057,0,0],"CostNum":[35,1,0,0]},{"_id":4113,"ExclusiveEquipId":4113,"ExclusiveEquipName":280000413,"ExclusiveEquipIcon":"ZSZB_zi_13","TeshuShuXingIcon":"","Quality":5,"DangCi":4,"Property":1,"ExclusiveEquipMiaoShu":280001313,"MaxUPgeade":30,"QiangHua":12,"MaxStar":1,"ExclusiveEquipStarAttr":2000000,"TeshuShuXingID":0,"TeshuJiNengFanYiID":0,"ExclusiveNinJas":0,"WNType":0,"WNID":0,"ExchangeID":0,"ExchangeCostType":0,"ExchangeCostID":0,"ExchangeCostCount":0,"JiBanJiNengIcon":[""],"TeshuJiNengStar":[0],"TeshuJiNengID":[0],"CostType":[2,2,0,0],"CostID":[6056,6057,0,0],"CostNum":[35,1,0,0]},{"_id":5101,"ExclusiveEquipId":5101,"ExclusiveEquipName":280000560,"ExclusiveEquipIcon":"ZSZB_Rider_01","TeshuShuXingIcon":"ZSZB_SX_01","Quality":7,"DangCi":5,"Property":1,"ExclusiveEquipMiaoShu":280001561,"MaxUPgeade":50,"QiangHua":22,"MaxStar":3,"ExclusiveEquipStarAttr":3000000,"TeshuShuXingID":60035101,"TeshuJiNengFanYiID":0,"ExclusiveNinJas":30703,"WNType":0,"WNID":0,"ExchangeID":0,"ExchangeCostType":0,"ExchangeCostID":0,"ExchangeCostCount":0,"JiBanJiNengIcon":["JN_06_Rider"],"TeshuJiNengStar":[2],"TeshuJiNengID":[3075111],"CostType":[2,2,2,1],"CostID":[6056,6057,9511,76],"CostNum":[50,2,1,900]},{"_id":5102,"ExclusiveEquipId":5102,"ExclusiveEquipName":280000562,"ExclusiveEquipIcon":"ZSZB_Nami_01","TeshuShuXingIcon":"ZSZB_SX_01","Quality":7,"DangCi":5,"Property":3,"ExclusiveEquipMiaoShu":280001562,"MaxUPgeade":50,"QiangHua":23,"MaxStar":3,"ExclusiveEquipStarAttr":3000000,"TeshuShuXingID":60035102,"TeshuJiNengFanYiID":0,"ExclusiveNinJas":31003,"WNType":0,"WNID":0,"ExchangeID":0,"ExchangeCostType":0,"ExchangeCostID":0,"ExchangeCostCount":0,"JiBanJiNengIcon":["JN_06_Nami"],"TeshuJiNengStar":[2],"TeshuJiNengID":[3105111],"CostType":[2,2,2,1],"CostID":[6056,6057,9511,76],"CostNum":[50,2,1,900]},{"_id":5103,"ExclusiveEquipId":5103,"ExclusiveEquipName":280000564,"ExclusiveEquipIcon":"ZSZB_Trunks_01","TeshuShuXingIcon":"ZSZB_SX_01","Quality":7,"DangCi":5,"Property":2,"ExclusiveEquipMiaoShu":280001563,"MaxUPgeade":50,"QiangHua":23,"MaxStar":3,"ExclusiveEquipStarAttr":3000000,"TeshuShuXingID":60035103,"TeshuJiNengFanYiID":0,"ExclusiveNinJas":31203,"WNType":0,"WNID":0,"ExchangeID":0,"ExchangeCostType":0,"ExchangeCostID":0,"ExchangeCostCount":0,"JiBanJiNengIcon":["JN_06_Trunks"],"TeshuJiNengStar":[2],"TeshuJiNengID":[3125111],"CostType":[2,2,2,1],"CostID":[6056,6057,9511,76],"CostNum":[50,2,1,900]},{"_id":5105,"ExclusiveEquipId":5105,"ExclusiveEquipName":280000568,"ExclusiveEquipIcon":"ZSZB_Tengen_01","TeshuShuXingIcon":"ZSZB_SX_01","Quality":7,"DangCi":6,"Property":3,"ExclusiveEquipMiaoShu":280001597,"MaxUPgeade":50,"QiangHua":21,"MaxStar":3,"ExclusiveEquipStarAttr":3000000,"TeshuShuXingID":60035105,"TeshuJiNengFanYiID":0,"ExclusiveNinJas":30103,"WNType":0,"WNID":0,"ExchangeID":0,"ExchangeCostType":0,"ExchangeCostID":0,"ExchangeCostCount":0,"JiBanJiNengIcon":["JN_06_Tengen"],"TeshuJiNengStar":[2],"TeshuJiNengID":[3016111],"CostType":[2,2,2,1],"CostID":[6056,6057,9511,76],"CostNum":[50,2,1,900]},{"_id":5106,"ExclusiveEquipId":5106,"ExclusiveEquipName":280000570,"ExclusiveEquipIcon":"ZSZB_Sakura_01","TeshuShuXingIcon":"ZSZB_SX_01","Quality":7,"DangCi":5,"Property":3,"ExclusiveEquipMiaoShu":280001566,"MaxUPgeade":50,"QiangHua":22,"MaxStar":3,"ExclusiveEquipStarAttr":3000000,"TeshuShuXingID":60035106,"TeshuJiNengFanYiID":0,"ExclusiveNinJas":30203,"WNType":0,"WNID":0,"ExchangeID":0,"ExchangeCostType":0,"ExchangeCostID":0,"ExchangeCostCount":0,"JiBanJiNengIcon":["JN_06_Sakura"],"TeshuJiNengStar":[2],"TeshuJiNengID":[3026111],"CostType":[2,2,2,1],"CostID":[6056,6057,9511,76],"CostNum":[50,2,1,900]},{"_id":5107,"ExclusiveEquipId":5107,"ExclusiveEquipName":280000572,"ExclusiveEquipIcon":"ZSZB_Naruto_01","TeshuShuXingIcon":"ZSZB_SX_01","Quality":7,"DangCi":5,"Property":3,"ExclusiveEquipMiaoShu":280001567,"MaxUPgeade":50,"QiangHua":23,"MaxStar":3,"ExclusiveEquipStarAttr":3000000,"TeshuShuXingID":60035107,"TeshuJiNengFanYiID":0,"ExclusiveNinJas":30303,"WNType":0,"WNID":0,"ExchangeID":0,"ExchangeCostType":0,"ExchangeCostID":0,"ExchangeCostCount":0,"JiBanJiNengIcon":["JN_06_Naruto"],"TeshuJiNengStar":[2],"TeshuJiNengID":[3036111],"CostType":[2,2,2,1],"CostID":[6056,6057,9511,76],"CostNum":[50,2,1,900]},{"_id":5108,"ExclusiveEquipId":5108,"ExclusiveEquipName":280000574,"ExclusiveEquipIcon":"ZSZB_Orihime_01","TeshuShuXingIcon":"ZSZB_SX_01","Quality":7,"DangCi":5,"Property":2,"ExclusiveEquipMiaoShu":280001568,"MaxUPgeade":50,"QiangHua":22,"MaxStar":3,"ExclusiveEquipStarAttr":3000000,"TeshuShuXingID":60035108,"TeshuJiNengFanYiID":0,"ExclusiveNinJas":30403,"WNType":0,"WNID":0,"ExchangeID":0,"ExchangeCostType":0,"ExchangeCostID":0,"ExchangeCostCount":0,"JiBanJiNengIcon":["JN_06_Orihime"],"TeshuJiNengStar":[2],"TeshuJiNengID":[3046111],"CostType":[2,2,2,1],"CostID":[6056,6057,9511,76],"CostNum":[50,2,1,900]},{"_id":5109,"ExclusiveEquipId":5109,"ExclusiveEquipName":280000576,"ExclusiveEquipIcon":"ZSZB_Cifer_01","TeshuShuXingIcon":"ZSZB_SX_01","Quality":7,"DangCi":5,"Property":1,"ExclusiveEquipMiaoShu":280001569,"MaxUPgeade":50,"QiangHua":23,"MaxStar":3,"ExclusiveEquipStarAttr":3000000,"TeshuShuXingID":60035109,"TeshuJiNengFanYiID":0,"ExclusiveNinJas":31703,"WNType":0,"WNID":0,"ExchangeID":0,"ExchangeCostType":0,"ExchangeCostID":0,"ExchangeCostCount":0,"JiBanJiNengIcon":["JN_06_Cifer"],"TeshuJiNengStar":[2],"TeshuJiNengID":[3176111],"CostType":[2,2,2,1],"CostID":[6056,6057,9511,76],"CostNum":[50,2,1,900]},{"_id":5112,"ExclusiveEquipId":5112,"ExclusiveEquipName":280000582,"ExclusiveEquipIcon":"ZSZB_Kirei_01","TeshuShuXingIcon":"ZSZB_SX_01","Quality":7,"DangCi":5,"Property":2,"ExclusiveEquipMiaoShu":280001572,"MaxUPgeade":50,"QiangHua":21,"MaxStar":3,"ExclusiveEquipStarAttr":3000000,"TeshuShuXingID":60035112,"TeshuJiNengFanYiID":0,"ExclusiveNinJas":31403,"WNType":0,"WNID":0,"ExchangeID":0,"ExchangeCostType":0,"ExchangeCostID":0,"ExchangeCostCount":0,"JiBanJiNengIcon":["JN_06_Kirei"],"TeshuJiNengStar":[2],"TeshuJiNengID":[3145111],"CostType":[2,2,2,1],"CostID":[6056,6057,9511,76],"CostNum":[50,2,1,900]},{"_id":5113,"ExclusiveEquipId":5113,"ExclusiveEquipName":280000647,"ExclusiveEquipIcon":"ZSZB_A_01","TeshuShuXingIcon":"ZSZB_SX_01","Quality":7,"DangCi":6,"Property":2,"ExclusiveEquipMiaoShu":280001613,"MaxUPgeade":50,"QiangHua":23,"MaxStar":3,"ExclusiveEquipStarAttr":3000000,"TeshuShuXingID":60035113,"TeshuJiNengFanYiID":0,"ExclusiveNinJas":30603,"WNType":0,"WNID":0,"ExchangeID":0,"ExchangeCostType":0,"ExchangeCostID":0,"ExchangeCostCount":0,"JiBanJiNengIcon":["JN_06_A"],"TeshuJiNengStar":[2],"TeshuJiNengID":[3065111],"CostType":[2,2,2,1],"CostID":[6056,6057,9511,76],"CostNum":[50,2,1,900]},{"_id":5115,"ExclusiveEquipId":5115,"ExclusiveEquipName":280000588,"ExclusiveEquipIcon":"ZSZB_Zoro_01","TeshuShuXingIcon":"ZSZB_SX_01","Quality":7,"DangCi":6,"Property":1,"ExclusiveEquipMiaoShu":280001575,"MaxUPgeade":50,"QiangHua":23,"MaxStar":3,"ExclusiveEquipStarAttr":3000000,"TeshuShuXingID":60035115,"TeshuJiNengFanYiID":0,"ExclusiveNinJas":30903,"WNType":0,"WNID":0,"ExchangeID":0,"ExchangeCostType":0,"ExchangeCostID":0,"ExchangeCostCount":0,"JiBanJiNengIcon":["JN_06_Zoro"],"TeshuJiNengStar":[2],"TeshuJiNengID":[3095111],"CostType":[2,2,2,1],"CostID":[6056,6057,9511,76],"CostNum":[50,2,1,900]},{"_id":5118,"ExclusiveEquipId":5118,"ExclusiveEquipName":280000594,"ExclusiveEquipIcon":"ZSZB_TodoAoi_01","TeshuShuXingIcon":"ZSZB_SX_01","Quality":7,"DangCi":5,"Property":1,"ExclusiveEquipMiaoShu":280001578,"MaxUPgeade":50,"QiangHua":21,"MaxStar":3,"ExclusiveEquipStarAttr":3000000,"TeshuShuXingID":60035118,"TeshuJiNengFanYiID":0,"ExclusiveNinJas":31603,"WNType":0,"WNID":0,"ExchangeID":0,"ExchangeCostType":0,"ExchangeCostID":0,"ExchangeCostCount":0,"JiBanJiNengIcon":["JN_06_TodoAoi"],"TeshuJiNengStar":[2],"TeshuJiNengID":[3167111],"CostType":[2,2,2,1],"CostID":[6056,6057,9511,76],"CostNum":[50,2,1,900]},{"_id":5119,"ExclusiveEquipId":5119,"ExclusiveEquipName":280000596,"ExclusiveEquipIcon":"ZSZB_Leafa_01","TeshuShuXingIcon":"ZSZB_SX_01","Quality":7,"DangCi":5,"Property":1,"ExclusiveEquipMiaoShu":280001579,"MaxUPgeade":50,"QiangHua":23,"MaxStar":3,"ExclusiveEquipStarAttr":3000000,"TeshuShuXingID":60035119,"TeshuJiNengFanYiID":0,"ExclusiveNinJas":31903,"WNType":0,"WNID":0,"ExchangeID":0,"ExchangeCostType":0,"ExchangeCostID":0,"ExchangeCostCount":0,"JiBanJiNengIcon":["JN_06_Leafa"],"TeshuJiNengStar":[2],"TeshuJiNengID":[3197111],"CostType":[2,2,2,1],"CostID":[6056,6057,9511,76],"CostNum":[50,2,1,900]},{"_id":5120,"ExclusiveEquipId":5120,"ExclusiveEquipName":280000598,"ExclusiveEquipIcon":"ZSZB_Itachi_01","TeshuShuXingIcon":"ZSZB_SX_01","Quality":7,"DangCi":7,"Property":5,"ExclusiveEquipMiaoShu":280001580,"MaxUPgeade":50,"QiangHua":23,"MaxStar":3,"ExclusiveEquipStarAttr":3000000,"TeshuShuXingID":60035120,"TeshuJiNengFanYiID":0,"ExclusiveNinJas":40103,"WNType":0,"WNID":0,"ExchangeID":0,"ExchangeCostType":0,"ExchangeCostID":0,"ExchangeCostCount":0,"JiBanJiNengIcon":["JN_06_Itachi"],"TeshuJiNengStar":[2],"TeshuJiNengID":[4015111],"CostType":[2,2,2,1],"CostID":[6056,6057,9511,76],"CostNum":[50,2,1,900]},{"_id":5121,"ExclusiveEquipId":5121,"ExclusiveEquipName":280000600,"ExclusiveEquipIcon":"ZSZB_Ace_01","TeshuShuXingIcon":"ZSZB_SX_01","Quality":7,"DangCi":6,"Property":3,"ExclusiveEquipMiaoShu":280001581,"MaxUPgeade":50,"QiangHua":23,"MaxStar":3,"ExclusiveEquipStarAttr":3000000,"TeshuShuXingID":60035121,"TeshuJiNengFanYiID":0,"ExclusiveNinJas":40203,"WNType":0,"WNID":0,"ExchangeID":0,"ExchangeCostType":0,"ExchangeCostID":0,"ExchangeCostCount":0,"JiBanJiNengIcon":["JN_06_Ace"],"TeshuJiNengStar":[2],"TeshuJiNengID":[4025111],"CostType":[2,2,2,1],"CostID":[6056,6057,9511,76],"CostNum":[50,2,1,900]},{"_id":5122,"ExclusiveEquipId":5122,"ExclusiveEquipName":280000602,"ExclusiveEquipIcon":"ZSZB_Vegeta_01","TeshuShuXingIcon":"ZSZB_SX_01","Quality":7,"DangCi":7,"Property":5,"ExclusiveEquipMiaoShu":280001582,"MaxUPgeade":50,"QiangHua":23,"MaxStar":3,"ExclusiveEquipStarAttr":3000000,"TeshuShuXingID":60035122,"TeshuJiNengFanYiID":0,"ExclusiveNinJas":40303,"WNType":0,"WNID":0,"ExchangeID":0,"ExchangeCostType":0,"ExchangeCostID":0,"ExchangeCostCount":0,"JiBanJiNengIcon":["JN_06_Vegeta"],"TeshuJiNengStar":[2],"TeshuJiNengID":[4035111],"CostType":[2,2,2,1],"CostID":[6056,6057,9511,76],"CostNum":[50,2,1,900]},{"_id":5123,"ExclusiveEquipId":5123,"ExclusiveEquipName":280000604,"ExclusiveEquipIcon":"ZSZB_Asuna_01","TeshuShuXingIcon":"ZSZB_SX_01","Quality":7,"DangCi":7,"Property":4,"ExclusiveEquipMiaoShu":280001583,"MaxUPgeade":50,"QiangHua":22,"MaxStar":3,"ExclusiveEquipStarAttr":3000000,"TeshuShuXingID":60035123,"TeshuJiNengFanYiID":0,"ExclusiveNinJas":40403,"WNType":0,"WNID":0,"ExchangeID":0,"ExchangeCostType":0,"ExchangeCostID":0,"ExchangeCostCount":0,"JiBanJiNengIcon":["JN_06_Asuna"],"TeshuJiNengStar":[2],"TeshuJiNengID":[4045111],"CostType":[2,2,2,1],"CostID":[6056,6057,9511,76],"CostNum":[50,2,1,900]},{"_id":5124,"ExclusiveEquipId":5124,"ExclusiveEquipName":280000606,"ExclusiveEquipIcon":"ZSZB_Kakashi_Kamui01","TeshuShuXingIcon":"ZSZB_SX_01","Quality":7,"DangCi":7,"Property":5,"ExclusiveEquipMiaoShu":280001584,"MaxUPgeade":50,"QiangHua":23,"MaxStar":3,"ExclusiveEquipStarAttr":3000000,"TeshuShuXingID":60035124,"TeshuJiNengFanYiID":0,"ExclusiveNinJas":40503,"WNType":0,"WNID":0,"ExchangeID":0,"ExchangeCostType":0,"ExchangeCostID":0,"ExchangeCostCount":0,"JiBanJiNengIcon":["JN_06_Kakashi_Kamui"],"TeshuJiNengStar":[2],"TeshuJiNengID":[4055111],"CostType":[2,2,2,1],"CostID":[6056,6057,9511,76],"CostNum":[50,2,1,900]},{"_id":5125,"ExclusiveEquipId":5125,"ExclusiveEquipName":280000608,"ExclusiveEquipIcon":"ZSZB_Kyo_01","TeshuShuXingIcon":"ZSZB_SX_01","Quality":7,"DangCi":7,"Property":4,"ExclusiveEquipMiaoShu":280001585,"MaxUPgeade":50,"QiangHua":23,"MaxStar":3,"ExclusiveEquipStarAttr":3000000,"TeshuShuXingID":60035125,"TeshuJiNengFanYiID":0,"ExclusiveNinJas":40603,"WNType":0,"WNID":0,"ExchangeID":0,"ExchangeCostType":0,"ExchangeCostID":0,"ExchangeCostCount":0,"JiBanJiNengIcon":["JN_06_Kyo"],"TeshuJiNengStar":[2],"TeshuJiNengID":[4065111],"CostType":[2,2,2,1],"CostID":[6056,6057,9511,76],"CostNum":[50,2,1,900]},{"_id":5126,"ExclusiveEquipId":5126,"ExclusiveEquipName":280000610,"ExclusiveEquipIcon":"ZSZB_Hancock_01","TeshuShuXingIcon":"ZSZB_SX_01","Quality":7,"DangCi":7,"Property":5,"ExclusiveEquipMiaoShu":280001586,"MaxUPgeade":50,"QiangHua":22,"MaxStar":3,"ExclusiveEquipStarAttr":3000000,"TeshuShuXingID":60035126,"TeshuJiNengFanYiID":0,"ExclusiveNinJas":40703,"WNType":0,"WNID":0,"ExchangeID":0,"ExchangeCostType":0,"ExchangeCostID":0,"ExchangeCostCount":0,"JiBanJiNengIcon":["JN_06_Hancock"],"TeshuJiNengStar":[2],"TeshuJiNengID":[4075111],"CostType":[2,2,2,1],"CostID":[6056,6057,9511,76],"CostNum":[50,2,1,900]},{"_id":5127,"ExclusiveEquipId":5127,"ExclusiveEquipName":280000612,"ExclusiveEquipIcon":"ZSZB_Emiya_01","TeshuShuXingIcon":"ZSZB_SX_01","Quality":7,"DangCi":7,"Property":4,"ExclusiveEquipMiaoShu":280001587,"MaxUPgeade":50,"QiangHua":21,"MaxStar":3,"ExclusiveEquipStarAttr":3000000,"TeshuShuXingID":60035127,"TeshuJiNengFanYiID":0,"ExclusiveNinJas":40803,"WNType":0,"WNID":0,"ExchangeID":0,"ExchangeCostType":0,"ExchangeCostID":0,"ExchangeCostCount":0,"JiBanJiNengIcon":["JN_06_Emiya"],"TeshuJiNengStar":[2],"TeshuJiNengID":[4085111],"CostType":[2,2,2,1],"CostID":[6056,6057,9511,76],"CostNum":[50,2,1,900]},{"_id":5128,"ExclusiveEquipId":5128,"ExclusiveEquipName":280000614,"ExclusiveEquipIcon":"ZSZB_Aizen_01","TeshuShuXingIcon":"ZSZB_SX_01","Quality":7,"DangCi":6,"Property":2,"ExclusiveEquipMiaoShu":280001588,"MaxUPgeade":50,"QiangHua":23,"MaxStar":3,"ExclusiveEquipStarAttr":3000000,"TeshuShuXingID":60035128,"TeshuJiNengFanYiID":0,"ExclusiveNinJas":40903,"WNType":0,"WNID":0,"ExchangeID":0,"ExchangeCostType":0,"ExchangeCostID":0,"ExchangeCostCount":0,"JiBanJiNengIcon":["JN_06_Aizen"],"TeshuJiNengStar":[2],"TeshuJiNengID":[4095111],"CostType":[2,2,2,1],"CostID":[6056,6057,9511,76],"CostNum":[50,2,1,900]},{"_id":5129,"ExclusiveEquipId":5129,"ExclusiveEquipName":280000616,"ExclusiveEquipIcon":"ZSZB_Megumi_01","TeshuShuXingIcon":"ZSZB_SX_01","Quality":7,"DangCi":6,"Property":1,"ExclusiveEquipMiaoShu":280001589,"MaxUPgeade":50,"QiangHua":23,"MaxStar":3,"ExclusiveEquipStarAttr":3000000,"TeshuShuXingID":60035129,"TeshuJiNengFanYiID":0,"ExclusiveNinJas":41003,"WNType":0,"WNID":0,"ExchangeID":0,"ExchangeCostType":0,"ExchangeCostID":0,"ExchangeCostCount":0,"JiBanJiNengIcon":["JN_06_Megumi"],"TeshuJiNengStar":[2],"TeshuJiNengID":[4105111],"CostType":[2,2,2,1],"CostID":[6056,6057,9511,76],"CostNum":[50,2,1,900]},{"_id":5130,"ExclusiveEquipId":5130,"ExclusiveEquipName":280000618,"ExclusiveEquipIcon":"ZSZB_Cell_01","TeshuShuXingIcon":"ZSZB_SX_01","Quality":7,"DangCi":6,"Property":3,"ExclusiveEquipMiaoShu":280001590,"MaxUPgeade":50,"QiangHua":23,"MaxStar":3,"ExclusiveEquipStarAttr":3000000,"TeshuShuXingID":60035130,"TeshuJiNengFanYiID":0,"ExclusiveNinJas":41103,"WNType":0,"WNID":0,"ExchangeID":0,"ExchangeCostType":0,"ExchangeCostID":0,"ExchangeCostCount":0,"JiBanJiNengIcon":["JN_06_Cell"],"TeshuJiNengStar":[2],"TeshuJiNengID":[4115111],"CostType":[2,2,2,1],"CostID":[6056,6057,9511,76],"CostNum":[50,2,1,900]},{"_id":5131,"ExclusiveEquipId":5131,"ExclusiveEquipName":280000620,"ExclusiveEquipIcon":"ZSZB_Tsunade_01","TeshuShuXingIcon":"ZSZB_SX_01","Quality":7,"DangCi":6,"Property":2,"ExclusiveEquipMiaoShu":280001591,"MaxUPgeade":50,"QiangHua":23,"MaxStar":3,"ExclusiveEquipStarAttr":3000000,"TeshuShuXingID":60035131,"TeshuJiNengFanYiID":0,"ExclusiveNinJas":41203,"WNType":0,"WNID":0,"ExchangeID":0,"ExchangeCostType":0,"ExchangeCostID":0,"ExchangeCostCount":0,"JiBanJiNengIcon":["JN_06_Tsunade"],"TeshuJiNengStar":[2],"TeshuJiNengID":[4125111],"CostType":[2,2,2,1],"CostID":[6056,6057,9511,76],"CostNum":[50,2,1,900]},{"_id":5132,"ExclusiveEquipId":5132,"ExclusiveEquipName":280000622,"ExclusiveEquipIcon":"ZSZB_Yuta_01","TeshuShuXingIcon":"ZSZB_SX_01","Quality":7,"DangCi":6,"Property":1,"ExclusiveEquipMiaoShu":280001592,"MaxUPgeade":50,"QiangHua":22,"MaxStar":3,"ExclusiveEquipStarAttr":3000000,"TeshuShuXingID":60035132,"TeshuJiNengFanYiID":0,"ExclusiveNinJas":41303,"WNType":0,"WNID":0,"ExchangeID":0,"ExchangeCostType":0,"ExchangeCostID":0,"ExchangeCostCount":0,"JiBanJiNengIcon":["JN_06_Yuta"],"TeshuJiNengStar":[2],"TeshuJiNengID":[4135111],"CostType":[2,2,2,1],"CostID":[6056,6057,9511,76],"CostNum":[50,2,1,900]},{"_id":5133,"ExclusiveEquipId":5133,"ExclusiveEquipName":280000624,"ExclusiveEquipIcon":"ZSZB_Frieza_01","TeshuShuXingIcon":"ZSZB_SX_01","Quality":7,"DangCi":6,"Property":2,"ExclusiveEquipMiaoShu":280001593,"MaxUPgeade":50,"QiangHua":23,"MaxStar":3,"ExclusiveEquipStarAttr":3000000,"TeshuShuXingID":60035133,"TeshuJiNengFanYiID":0,"ExclusiveNinJas":41403,"WNType":0,"WNID":0,"ExchangeID":0,"ExchangeCostType":0,"ExchangeCostID":0,"ExchangeCostCount":0,"JiBanJiNengIcon":["JN_06_Frieza"],"TeshuJiNengStar":[2],"TeshuJiNengID":[4145111],"CostType":[2,2,2,1],"CostID":[6056,6057,9511,76],"CostNum":[50,2,1,900]},{"_id":5134,"ExclusiveEquipId":5134,"ExclusiveEquipName":280000626,"ExclusiveEquipIcon":"ZSZB_Chopper_01","TeshuShuXingIcon":"ZSZB_SX_01","Quality":7,"DangCi":6,"Property":2,"ExclusiveEquipMiaoShu":280001594,"MaxUPgeade":50,"QiangHua":22,"MaxStar":3,"ExclusiveEquipStarAttr":3000000,"TeshuShuXingID":60035134,"TeshuJiNengFanYiID":0,"ExclusiveNinJas":41503,"WNType":0,"WNID":0,"ExchangeID":0,"ExchangeCostType":0,"ExchangeCostID":0,"ExchangeCostCount":0,"JiBanJiNengIcon":["JN_06_Chopper"],"TeshuJiNengStar":[2],"TeshuJiNengID":[4155111],"CostType":[2,2,2,1],"CostID":[6056,6057,9511,76],"CostNum":[50,2,1,900]},{"_id":5135,"ExclusiveEquipId":5135,"ExclusiveEquipName":280000628,"ExclusiveEquipIcon":"ZSZB_Ichigo_01","TeshuShuXingIcon":"ZSZB_SX_01","Quality":7,"DangCi":7,"Property":5,"ExclusiveEquipMiaoShu":280001595,"MaxUPgeade":50,"QiangHua":23,"MaxStar":3,"ExclusiveEquipStarAttr":3000000,"TeshuShuXingID":60035135,"TeshuJiNengFanYiID":0,"ExclusiveNinJas":41603,"WNType":0,"WNID":0,"ExchangeID":0,"ExchangeCostType":0,"ExchangeCostID":0,"ExchangeCostCount":0,"JiBanJiNengIcon":["JN_06_Ichigo"],"TeshuJiNengStar":[2],"TeshuJiNengID":[4165111],"CostType":[2,2,2,1],"CostID":[6056,6057,9511,76],"CostNum":[50,2,1,900]},{"_id":5136,"ExclusiveEquipId":5136,"ExclusiveEquipName":280000630,"ExclusiveEquipIcon":"ZSZB_SonGoKu_01","TeshuShuXingIcon":"ZSZB_SX_01","Quality":7,"DangCi":7,"Property":4,"ExclusiveEquipMiaoShu":280001596,"MaxUPgeade":50,"QiangHua":23,"MaxStar":3,"ExclusiveEquipStarAttr":3000000,"TeshuShuXingID":60035136,"TeshuJiNengFanYiID":0,"ExclusiveNinJas":41703,"WNType":0,"WNID":0,"ExchangeID":0,"ExchangeCostType":0,"ExchangeCostID":0,"ExchangeCostCount":0,"JiBanJiNengIcon":["JN_06_SonGoKu"],"TeshuJiNengStar":[2],"TeshuJiNengID":[4175111],"CostType":[2,2,2,1],"CostID":[6056,6057,9511,76],"CostNum":[50,2,1,900]},{"_id":5137,"ExclusiveEquipId":5137,"ExclusiveEquipName":280000631,"ExclusiveEquipIcon":"ZSZB_Yuji_01","TeshuShuXingIcon":"ZSZB_SX_01","Quality":7,"DangCi":6,"Property":3,"ExclusiveEquipMiaoShu":280001565,"MaxUPgeade":50,"QiangHua":23,"MaxStar":3,"ExclusiveEquipStarAttr":3000000,"TeshuShuXingID":60035137,"TeshuJiNengFanYiID":0,"ExclusiveNinJas":32003,"WNType":0,"WNID":0,"ExchangeID":0,"ExchangeCostType":0,"ExchangeCostID":0,"ExchangeCostCount":0,"JiBanJiNengIcon":["JN_06_Yuji"],"TeshuJiNengStar":[2],"TeshuJiNengID":[3205111],"CostType":[2,2,2,1],"CostID":[6056,6057,9511,76],"CostNum":[50,2,1,900]},{"_id":5138,"ExclusiveEquipId":5138,"ExclusiveEquipName":280000632,"ExclusiveEquipIcon":"ZSZB_Nezuko_01","TeshuShuXingIcon":"ZSZB_SX_01","Quality":7,"DangCi":7,"Property":5,"ExclusiveEquipMiaoShu":280001598,"MaxUPgeade":50,"QiangHua":21,"MaxStar":3,"ExclusiveEquipStarAttr":3000000,"TeshuShuXingID":60035138,"TeshuJiNengFanYiID":0,"ExclusiveNinJas":41803,"WNType":0,"WNID":0,"ExchangeID":0,"ExchangeCostType":0,"ExchangeCostID":0,"ExchangeCostCount":0,"JiBanJiNengIcon":["JN_06_Nezuko"],"TeshuJiNengStar":[2],"TeshuJiNengID":[4185111],"CostType":[2,2,2,1],"CostID":[6056,6057,9511,76],"CostNum":[50,2,1,900]},{"_id":5139,"ExclusiveEquipId":5139,"ExclusiveEquipName":280000633,"ExclusiveEquipIcon":"ZSZB_Gintoki_01","TeshuShuXingIcon":"ZSZB_SX_01","Quality":7,"DangCi":6,"Property":1,"ExclusiveEquipMiaoShu":280001599,"MaxUPgeade":50,"QiangHua":21,"MaxStar":3,"ExclusiveEquipStarAttr":3000000,"TeshuShuXingID":60035139,"TeshuJiNengFanYiID":0,"ExclusiveNinJas":41903,"WNType":0,"WNID":0,"ExchangeID":0,"ExchangeCostType":0,"ExchangeCostID":0,"ExchangeCostCount":0,"JiBanJiNengIcon":["JN_06_Gintoki"],"TeshuJiNengStar":[2],"TeshuJiNengID":[4195111],"CostType":[2,2,2,1],"CostID":[6056,6057,9511,76],"CostNum":[50,2,1,900]},{"_id":5140,"ExclusiveEquipId":5140,"ExclusiveEquipName":280000634,"ExclusiveEquipIcon":"ZSZB_Athena_01","TeshuShuXingIcon":"ZSZB_SX_01","Quality":7,"DangCi":7,"Property":4,"ExclusiveEquipMiaoShu":280001600,"MaxUPgeade":50,"QiangHua":22,"MaxStar":3,"ExclusiveEquipStarAttr":3000000,"TeshuShuXingID":60035140,"TeshuJiNengFanYiID":0,"ExclusiveNinJas":42003,"WNType":0,"WNID":0,"ExchangeID":0,"ExchangeCostType":0,"ExchangeCostID":0,"ExchangeCostCount":0,"JiBanJiNengIcon":["JN_06_Athena"],"TeshuJiNengStar":[2],"TeshuJiNengID":[4205111],"CostType":[2,2,2,1],"CostID":[6056,6057,9511,76],"CostNum":[50,2,1,900]},{"_id":5141,"ExclusiveEquipId":5141,"ExclusiveEquipName":280000635,"ExclusiveEquipIcon":"ZSZB_Levi_01","TeshuShuXingIcon":"ZSZB_SX_01","Quality":7,"DangCi":6,"Property":3,"ExclusiveEquipMiaoShu":280001601,"MaxUPgeade":50,"QiangHua":23,"MaxStar":3,"ExclusiveEquipStarAttr":3000000,"TeshuShuXingID":60035141,"TeshuJiNengFanYiID":0,"ExclusiveNinJas":42103,"WNType":0,"WNID":0,"ExchangeID":0,"ExchangeCostType":0,"ExchangeCostID":0,"ExchangeCostCount":0,"JiBanJiNengIcon":["JN_06_Levi"],"TeshuJiNengStar":[2],"TeshuJiNengID":[4215111],"CostType":[2,2,2,1],"CostID":[6056,6057,9511,76],"CostNum":[50,2,1,900]},{"_id":5142,"ExclusiveEquipId":5142,"ExclusiveEquipName":280000636,"ExclusiveEquipIcon":"ZSZB_Killua_01","TeshuShuXingIcon":"ZSZB_SX_01","Quality":7,"DangCi":6,"Property":1,"ExclusiveEquipMiaoShu":280001602,"MaxUPgeade":50,"QiangHua":23,"MaxStar":3,"ExclusiveEquipStarAttr":3000000,"TeshuShuXingID":60035142,"TeshuJiNengFanYiID":0,"ExclusiveNinJas":43503,"WNType":0,"WNID":0,"ExchangeID":0,"ExchangeCostType":0,"ExchangeCostID":0,"ExchangeCostCount":0,"JiBanJiNengIcon":["JN_06_Killua"],"TeshuJiNengStar":[2],"TeshuJiNengID":[4355111],"CostType":[2,2,2,1],"CostID":[6056,6057,9511,76],"CostNum":[50,2,1,900]},{"_id":5143,"ExclusiveEquipId":5143,"ExclusiveEquipName":280000637,"ExclusiveEquipIcon":"ZSZB_Shino_01","TeshuShuXingIcon":"ZSZB_SX_01","Quality":7,"DangCi":6,"Property":3,"ExclusiveEquipMiaoShu":280001603,"MaxUPgeade":50,"QiangHua":23,"MaxStar":3,"ExclusiveEquipStarAttr":3000000,"TeshuShuXingID":60035143,"TeshuJiNengFanYiID":0,"ExclusiveNinJas":42203,"WNType":0,"WNID":0,"ExchangeID":0,"ExchangeCostType":0,"ExchangeCostID":0,"ExchangeCostCount":0,"JiBanJiNengIcon":["JN_06_Shino"],"TeshuJiNengStar":[2],"TeshuJiNengID":[4225111],"CostType":[2,2,2,1],"CostID":[6056,6057,9511,76],"CostNum":[50,3,1,900]},{"_id":5144,"ExclusiveEquipId":5144,"ExclusiveEquipName":280000638,"ExclusiveEquipIcon":"ZSZB_Kyoujurou_01","TeshuShuXingIcon":"ZSZB_SX_01","Quality":7,"DangCi":7,"Property":4,"ExclusiveEquipMiaoShu":280001604,"MaxUPgeade":50,"QiangHua":21,"MaxStar":3,"ExclusiveEquipStarAttr":3000000,"TeshuShuXingID":60035144,"TeshuJiNengFanYiID":0,"ExclusiveNinJas":42303,"WNType":0,"WNID":0,"ExchangeID":0,"ExchangeCostType":0,"ExchangeCostID":0,"ExchangeCostCount":0,"JiBanJiNengIcon":["JN_06_Kyoujurou"],"TeshuJiNengStar":[2],"TeshuJiNengID":[4235111],"CostType":[2,2,2,1],"CostID":[6056,6057,9511,76],"CostNum":[50,3,1,900]},{"_id":5145,"ExclusiveEquipId":5145,"ExclusiveEquipName":280000639,"ExclusiveEquipIcon":"ZSZB_Shiryu_01","TeshuShuXingIcon":"ZSZB_SX_01","Quality":7,"DangCi":6,"Property":2,"ExclusiveEquipMiaoShu":280001605,"MaxUPgeade":50,"QiangHua":21,"MaxStar":3,"ExclusiveEquipStarAttr":3000000,"TeshuShuXingID":60035145,"TeshuJiNengFanYiID":0,"ExclusiveNinJas":42403,"WNType":0,"WNID":0,"ExchangeID":0,"ExchangeCostType":0,"ExchangeCostID":0,"ExchangeCostCount":0,"JiBanJiNengIcon":["JN_06_Shiryu"],"TeshuJiNengStar":[2],"TeshuJiNengID":[4245111],"CostType":[2,2,2,1],"CostID":[6056,6057,9511,76],"CostNum":[50,3,1,900]},{"_id":5146,"ExclusiveEquipId":5146,"ExclusiveEquipName":280000640,"ExclusiveEquipIcon":"ZSZB_Natsu_01","TeshuShuXingIcon":"ZSZB_SX_01","Quality":7,"DangCi":8,"Property":5,"ExclusiveEquipMiaoShu":280001606,"MaxUPgeade":50,"QiangHua":23,"MaxStar":3,"ExclusiveEquipStarAttr":3000000,"TeshuShuXingID":60035146,"TeshuJiNengFanYiID":0,"ExclusiveNinJas":42503,"WNType":0,"WNID":0,"ExchangeID":0,"ExchangeCostType":0,"ExchangeCostID":0,"ExchangeCostCount":0,"JiBanJiNengIcon":["JN_06_Natsu"],"TeshuJiNengStar":[2],"TeshuJiNengID":[4255111],"CostType":[2,2,2,1],"CostID":[6056,6057,9511,76],"CostNum":[50,3,1,900]},{"_id":5147,"ExclusiveEquipId":5147,"ExclusiveEquipName":280000641,"ExclusiveEquipIcon":"ZSZB_RoyMustang_01","TeshuShuXingIcon":"ZSZB_SX_01","Quality":7,"DangCi":7,"Property":5,"ExclusiveEquipMiaoShu":280001607,"MaxUPgeade":50,"QiangHua":22,"MaxStar":3,"ExclusiveEquipStarAttr":3000000,"TeshuShuXingID":60035147,"TeshuJiNengFanYiID":0,"ExclusiveNinJas":42603,"WNType":0,"WNID":0,"ExchangeID":0,"ExchangeCostType":0,"ExchangeCostID":0,"ExchangeCostCount":0,"JiBanJiNengIcon":["JN_06_RoyMustang"],"TeshuJiNengStar":[2],"TeshuJiNengID":[4265111],"CostType":[2,2,2,1],"CostID":[6056,6057,9511,76],"CostNum":[50,3,1,900]},{"_id":5148,"ExclusiveEquipId":5148,"ExclusiveEquipName":280000642,"ExclusiveEquipIcon":"ZSZB_Kurama_01","TeshuShuXingIcon":"ZSZB_SX_01","Quality":7,"DangCi":6,"Property":1,"ExclusiveEquipMiaoShu":280001608,"MaxUPgeade":50,"QiangHua":23,"MaxStar":3,"ExclusiveEquipStarAttr":3000000,"TeshuShuXingID":60035148,"TeshuJiNengFanYiID":0,"ExclusiveNinJas":42703,"WNType":0,"WNID":0,"ExchangeID":0,"ExchangeCostType":0,"ExchangeCostID":0,"ExchangeCostCount":0,"JiBanJiNengIcon":["JN_06_Kurama"],"TeshuJiNengStar":[2],"TeshuJiNengID":[4275111],"CostType":[2,2,2,1],"CostID":[6056,6057,9511,76],"CostNum":[45,3,1,900]},{"_id":5149,"ExclusiveEquipId":5149,"ExclusiveEquipName":280000643,"ExclusiveEquipIcon":"ZSZB_Rem_01","TeshuShuXingIcon":"ZSZB_SX_01","Quality":7,"DangCi":7,"Property":7,"ExclusiveEquipMiaoShu":280001609,"MaxUPgeade":50,"QiangHua":22,"MaxStar":3,"ExclusiveEquipStarAttr":3000000,"TeshuShuXingID":60035149,"TeshuJiNengFanYiID":0,"ExclusiveNinJas":42803,"WNType":0,"WNID":0,"ExchangeID":0,"ExchangeCostType":0,"ExchangeCostID":0,"ExchangeCostCount":0,"JiBanJiNengIcon":["JN_06_Rem"],"TeshuJiNengStar":[2],"TeshuJiNengID":[4285111],"CostType":[2,2,2,1],"CostID":[6056,6057,9511,76],"CostNum":[45,3,1,900]},{"_id":5150,"ExclusiveEquipId":5150,"ExclusiveEquipName":280000644,"ExclusiveEquipIcon":"ZSZB_Misaka_01","TeshuShuXingIcon":"ZSZB_SX_01","Quality":7,"DangCi":8,"Property":4,"ExclusiveEquipMiaoShu":280001610,"MaxUPgeade":50,"QiangHua":23,"MaxStar":3,"ExclusiveEquipStarAttr":3000000,"TeshuShuXingID":60035150,"TeshuJiNengFanYiID":0,"ExclusiveNinJas":42903,"WNType":0,"WNID":0,"ExchangeID":0,"ExchangeCostType":0,"ExchangeCostID":0,"ExchangeCostCount":0,"JiBanJiNengIcon":["JN_06_Misaka"],"TeshuJiNengStar":[2],"TeshuJiNengID":[4295111],"CostType":[2,2,2,1],"CostID":[6056,6057,9511,76],"CostNum":[45,3,1,900]},{"_id":5151,"ExclusiveEquipId":5151,"ExclusiveEquipName":280000645,"ExclusiveEquipIcon":"ZSZB_Pain_01","TeshuShuXingIcon":"ZSZB_SX_01","Quality":7,"DangCi":8,"Property":5,"ExclusiveEquipMiaoShu":280001611,"MaxUPgeade":50,"QiangHua":23,"MaxStar":3,"ExclusiveEquipStarAttr":3000000,"TeshuShuXingID":60035151,"TeshuJiNengFanYiID":0,"ExclusiveNinJas":43003,"WNType":0,"WNID":0,"ExchangeID":0,"ExchangeCostType":0,"ExchangeCostID":0,"ExchangeCostCount":0,"JiBanJiNengIcon":["JN_06_Pain"],"TeshuJiNengStar":[2],"TeshuJiNengID":[4305111],"CostType":[2,2,2,1],"CostID":[6056,6057,9511,76],"CostNum":[45,3,1,900]},{"_id":5152,"ExclusiveEquipId":5152,"ExclusiveEquipName":280000646,"ExclusiveEquipIcon":"ZSZB_Edward_01","TeshuShuXingIcon":"ZSZB_SX_01","Quality":7,"DangCi":8,"Property":4,"ExclusiveEquipMiaoShu":280001612,"MaxUPgeade":50,"QiangHua":21,"MaxStar":3,"ExclusiveEquipStarAttr":3000000,"TeshuShuXingID":60035152,"TeshuJiNengFanYiID":0,"ExclusiveNinJas":43103,"WNType":0,"WNID":0,"ExchangeID":0,"ExchangeCostType":0,"ExchangeCostID":0,"ExchangeCostCount":0,"JiBanJiNengIcon":["JN_06_Edward"],"TeshuJiNengStar":[2],"TeshuJiNengID":[4315111],"CostType":[2,2,2,1],"CostID":[6056,6057,9511,76],"CostNum":[45,3,1,900]},{"_id":5154,"ExclusiveEquipId":5154,"ExclusiveEquipName":280000648,"ExclusiveEquipIcon":"ZSZB_Saber_01","TeshuShuXingIcon":"ZSZB_SX_01","Quality":7,"DangCi":8,"Property":4,"ExclusiveEquipMiaoShu":280001614,"MaxUPgeade":50,"QiangHua":23,"MaxStar":3,"ExclusiveEquipStarAttr":3000000,"TeshuShuXingID":60035154,"TeshuJiNengFanYiID":0,"ExclusiveNinJas":43403,"WNType":0,"WNID":0,"ExchangeID":0,"ExchangeCostType":0,"ExchangeCostID":0,"ExchangeCostCount":0,"JiBanJiNengIcon":["JN_06_Saber"],"TeshuJiNengStar":[2],"TeshuJiNengID":[4345111],"CostType":[2,2,2,1],"CostID":[6056,6057,9511,76],"CostNum":[45,3,1,900]},{"_id":5155,"ExclusiveEquipId":5155,"ExclusiveEquipName":280000649,"ExclusiveEquipIcon":"ZSZB_Gojo_01","TeshuShuXingIcon":"ZSZB_SX_01","Quality":7,"DangCi":8,"Property":5,"ExclusiveEquipMiaoShu":280001615,"MaxUPgeade":50,"QiangHua":23,"MaxStar":3,"ExclusiveEquipStarAttr":3000000,"TeshuShuXingID":60035155,"TeshuJiNengFanYiID":0,"ExclusiveNinJas":43603,"WNType":0,"WNID":0,"ExchangeID":0,"ExchangeCostType":0,"ExchangeCostID":0,"ExchangeCostCount":0,"JiBanJiNengIcon":["JN_06_Gojo"],"TeshuJiNengStar":[2],"TeshuJiNengID":[4365111],"CostType":[2,2,2,1],"CostID":[6056,6057,9511,76],"CostNum":[45,3,1,900]},{"_id":5156,"ExclusiveEquipId":5156,"ExclusiveEquipName":280000650,"ExclusiveEquipIcon":"ZSZB_Josuke_01","TeshuShuXingIcon":"ZSZB_SX_01","Quality":7,"DangCi":8,"Property":4,"ExclusiveEquipMiaoShu":280001616,"MaxUPgeade":50,"QiangHua":22,"MaxStar":3,"ExclusiveEquipStarAttr":3000000,"TeshuShuXingID":60035156,"TeshuJiNengFanYiID":0,"ExclusiveNinJas":43703,"WNType":0,"WNID":0,"ExchangeID":0,"ExchangeCostType":0,"ExchangeCostID":0,"ExchangeCostCount":0,"JiBanJiNengIcon":["JN_06_Josuke"],"TeshuJiNengStar":[2],"TeshuJiNengID":[4375111],"CostType":[2,2,2,1],"CostID":[6056,6057,9511,76],"CostNum":[45,3,1,900]},{"_id":5157,"ExclusiveEquipId":5157,"ExclusiveEquipName":280000651,"ExclusiveEquipIcon":"ZSZB_Fern_01","TeshuShuXingIcon":"ZSZB_SX_01","Quality":7,"DangCi":8,"Property":7,"ExclusiveEquipMiaoShu":280001617,"MaxUPgeade":50,"QiangHua":23,"MaxStar":3,"ExclusiveEquipStarAttr":3000000,"TeshuShuXingID":60035157,"TeshuJiNengFanYiID":0,"ExclusiveNinJas":43803,"WNType":0,"WNID":0,"ExchangeID":0,"ExchangeCostType":0,"ExchangeCostID":0,"ExchangeCostCount":0,"JiBanJiNengIcon":["JN_06_Fern"],"TeshuJiNengStar":[2],"TeshuJiNengID":[4385111],"CostType":[2,2,2,1],"CostID":[6056,6057,9511,76],"CostNum":[45,3,1,900]},{"_id":5158,"ExclusiveEquipId":5158,"ExclusiveEquipName":280000652,"ExclusiveEquipIcon":"ZSZB_Kazuto_01","TeshuShuXingIcon":"ZSZB_SX_01","Quality":7,"DangCi":8,"Property":5,"ExclusiveEquipMiaoShu":280001618,"MaxUPgeade":50,"QiangHua":23,"MaxStar":3,"ExclusiveEquipStarAttr":3000000,"TeshuShuXingID":60035158,"TeshuJiNengFanYiID":0,"ExclusiveNinJas":43903,"WNType":0,"WNID":0,"ExchangeID":0,"ExchangeCostType":0,"ExchangeCostID":0,"ExchangeCostCount":0,"JiBanJiNengIcon":["JN_06_Kazuto"],"TeshuJiNengStar":[2],"TeshuJiNengID":[4395111],"CostType":[2,2,2,1],"CostID":[6056,6057,9511,76],"CostNum":[45,3,1,900]},{"_id":5159,"ExclusiveEquipId":5159,"ExclusiveEquipName":280000653,"ExclusiveEquipIcon":"ZSZB_Denji_01","TeshuShuXingIcon":"ZSZB_SX_01","Quality":7,"DangCi":8,"Property":4,"ExclusiveEquipMiaoShu":280001619,"MaxUPgeade":50,"QiangHua":21,"MaxStar":3,"ExclusiveEquipStarAttr":3000000,"TeshuShuXingID":60035159,"TeshuJiNengFanYiID":0,"ExclusiveNinJas":44003,"WNType":0,"WNID":0,"ExchangeID":0,"ExchangeCostType":0,"ExchangeCostID":0,"ExchangeCostCount":0,"JiBanJiNengIcon":["JN_06_Denji"],"TeshuJiNengStar":[2],"TeshuJiNengID":[4405111],"CostType":[2,2,2,1],"CostID":[6056,6057,9511,76],"CostNum":[45,3,1,900]},{"_id":5160,"ExclusiveEquipId":5160,"ExclusiveEquipName":280000654,"ExclusiveEquipIcon":"ZSZB_Frieren_01","TeshuShuXingIcon":"ZSZB_SX_01","Quality":7,"DangCi":8,"Property":4,"ExclusiveEquipMiaoShu":280001620,"MaxUPgeade":50,"QiangHua":23,"MaxStar":3,"ExclusiveEquipStarAttr":3000000,"TeshuShuXingID":60035160,"TeshuJiNengFanYiID":0,"ExclusiveNinJas":44103,"WNType":0,"WNID":0,"ExchangeID":0,"ExchangeCostType":0,"ExchangeCostID":0,"ExchangeCostCount":0,"JiBanJiNengIcon":["JN_06_Frieren"],"TeshuJiNengStar":[2],"TeshuJiNengID":[4415111],"CostType":[2,2,2,1],"CostID":[6056,6057,9511,76],"CostNum":[45,3,1,900]},{"_id":5161,"ExclusiveEquipId":5161,"ExclusiveEquipName":280000655,"ExclusiveEquipIcon":"ZSZB_Gilgamesh_01","TeshuShuXingIcon":"ZSZB_SX_01","Quality":7,"DangCi":8,"Property":5,"ExclusiveEquipMiaoShu":280001621,"MaxUPgeade":50,"QiangHua":23,"MaxStar":3,"ExclusiveEquipStarAttr":3000000,"TeshuShuXingID":60035161,"TeshuJiNengFanYiID":0,"ExclusiveNinJas":44203,"WNType":0,"WNID":0,"ExchangeID":0,"ExchangeCostType":0,"ExchangeCostID":0,"ExchangeCostCount":0,"JiBanJiNengIcon":["JN_06_Gilgamesh"],"TeshuJiNengStar":[2],"TeshuJiNengID":[4425111],"CostType":[2,2,2,1],"CostID":[6056,6057,9511,76],"CostNum":[45,3,1,900]},{"_id":5162,"ExclusiveEquipId":5162,"ExclusiveEquipName":280000656,"ExclusiveEquipIcon":"ZSZB_Berserker_01","TeshuShuXingIcon":"ZSZB_SX_01","Quality":7,"DangCi":8,"Property":5,"ExclusiveEquipMiaoShu":280001622,"MaxUPgeade":50,"QiangHua":23,"MaxStar":3,"ExclusiveEquipStarAttr":3000000,"TeshuShuXingID":60035162,"TeshuJiNengFanYiID":0,"ExclusiveNinJas":44303,"WNType":0,"WNID":0,"ExchangeID":0,"ExchangeCostType":0,"ExchangeCostID":0,"ExchangeCostCount":0,"JiBanJiNengIcon":["JN_06_Berserker"],"TeshuJiNengStar":[2],"TeshuJiNengID":[4435111],"CostType":[2,2,2,1],"CostID":[6056,6057,9511,76],"CostNum":[45,3,1,900]},{"_id":5163,"ExclusiveEquipId":5163,"ExclusiveEquipName":280000657,"ExclusiveEquipIcon":"ZSZB_Shaka_01","TeshuShuXingIcon":"ZSZB_SX_01","Quality":7,"DangCi":8,"Property":4,"ExclusiveEquipMiaoShu":280001623,"MaxUPgeade":50,"QiangHua":21,"MaxStar":3,"ExclusiveEquipStarAttr":3000000,"TeshuShuXingID":60035163,"TeshuJiNengFanYiID":0,"ExclusiveNinJas":44403,"WNType":0,"WNID":0,"ExchangeID":0,"ExchangeCostType":0,"ExchangeCostID":0,"ExchangeCostCount":0,"JiBanJiNengIcon":["JN_06_Shaka"],"TeshuJiNengStar":[2],"TeshuJiNengID":[4445111],"CostType":[2,2,2,1],"CostID":[6056,6057,9511,76],"CostNum":[45,3,1,900]},{"_id":5164,"ExclusiveEquipId":5164,"ExclusiveEquipName":280000658,"ExclusiveEquipIcon":"ZSZB_Lacus_01","TeshuShuXingIcon":"ZSZB_SX_01","Quality":7,"DangCi":8,"Property":5,"ExclusiveEquipMiaoShu":280001624,"MaxUPgeade":50,"QiangHua":22,"MaxStar":3,"ExclusiveEquipStarAttr":3000000,"TeshuShuXingID":60035164,"TeshuJiNengFanYiID":0,"ExclusiveNinJas":44503,"WNType":0,"WNID":0,"ExchangeID":0,"ExchangeCostType":0,"ExchangeCostID":0,"ExchangeCostCount":0,"JiBanJiNengIcon":["JN_06_Lacus"],"TeshuJiNengStar":[2],"TeshuJiNengID":[4455111],"CostType":[2,2,2,1],"CostID":[6056,6057,9511,76],"CostNum":[45,3,1,900]},{"_id":5165,"ExclusiveEquipId":5165,"ExclusiveEquipName":280000659,"ExclusiveEquipIcon":"ZSZB_Jinwoo_01","TeshuShuXingIcon":"ZSZB_SX_01","Quality":7,"DangCi":8,"Property":4,"ExclusiveEquipMiaoShu":280001625,"MaxUPgeade":50,"QiangHua":23,"MaxStar":3,"ExclusiveEquipStarAttr":3000000,"TeshuShuXingID":60035165,"TeshuJiNengFanYiID":0,"ExclusiveNinJas":44603,"WNType":0,"WNID":0,"ExchangeID":0,"ExchangeCostType":0,"ExchangeCostID":0,"ExchangeCostCount":0,"JiBanJiNengIcon":["JN_06_Jinwoo"],"TeshuJiNengStar":[2],"TeshuJiNengID":[4465111],"CostType":[2,2,2,1],"CostID":[6056,6057,9511,76],"CostNum":[45,3,1,900]},{"_id":5166,"ExclusiveEquipId":5166,"ExclusiveEquipName":280000660,"ExclusiveEquipIcon":"ZSZB_Soshiro_01","TeshuShuXingIcon":"ZSZB_SX_01","Quality":7,"DangCi":8,"Property":5,"ExclusiveEquipMiaoShu":280001626,"MaxUPgeade":50,"QiangHua":23,"MaxStar":3,"ExclusiveEquipStarAttr":3000000,"TeshuShuXingID":60035166,"TeshuJiNengFanYiID":0,"ExclusiveNinJas":44703,"WNType":0,"WNID":0,"ExchangeID":0,"ExchangeCostType":0,"ExchangeCostID":0,"ExchangeCostCount":0,"JiBanJiNengIcon":["JN_06_Soshiro"],"TeshuJiNengStar":[2],"TeshuJiNengID":[4475111],"CostType":[2,2,2,1],"CostID":[6056,6057,9511,76],"CostNum":[45,3,1,900]},{"_id":5167,"ExclusiveEquipId":5167,"ExclusiveEquipName":280000661,"ExclusiveEquipIcon":"ZSZB_Ainz_01","TeshuShuXingIcon":"ZSZB_SX_01","Quality":7,"DangCi":8,"Property":5,"ExclusiveEquipMiaoShu":280001627,"MaxUPgeade":50,"QiangHua":23,"MaxStar":3,"ExclusiveEquipStarAttr":3000000,"TeshuShuXingID":60035167,"TeshuJiNengFanYiID":0,"ExclusiveNinJas":44803,"WNType":0,"WNID":0,"ExchangeID":0,"ExchangeCostType":0,"ExchangeCostID":0,"ExchangeCostCount":0,"JiBanJiNengIcon":["JN_06_Ainz"],"TeshuJiNengStar":[2],"TeshuJiNengID":[4485111],"CostType":[2,2,2,1],"CostID":[6056,6057,9511,76],"CostNum":[45,3,1,900]},{"_id":5168,"ExclusiveEquipId":5168,"ExclusiveEquipName":280000662,"ExclusiveEquipIcon":"ZSZB_LiuDaoBan_01","TeshuShuXingIcon":"ZSZB_SX_01","Quality":7,"DangCi":8,"Property":4,"ExclusiveEquipMiaoShu":280001628,"MaxUPgeade":50,"QiangHua":23,"MaxStar":3,"ExclusiveEquipStarAttr":3000000,"TeshuShuXingID":60035168,"TeshuJiNengFanYiID":0,"ExclusiveNinJas":44903,"WNType":0,"WNID":0,"ExchangeID":0,"ExchangeCostType":0,"ExchangeCostID":0,"ExchangeCostCount":0,"JiBanJiNengIcon":["JN_05_Madara"],"TeshuJiNengStar":[2],"TeshuJiNengID":[4495111],"CostType":[2,2,2,1],"CostID":[6056,6057,9511,76],"CostNum":[45,3,1,900]},{"_id":5169,"ExclusiveEquipId":5169,"ExclusiveEquipName":280000663,"ExclusiveEquipIcon":"ZSZB_Kurumi_01","TeshuShuXingIcon":"ZSZB_SX_01","Quality":7,"DangCi":8,"Property":7,"ExclusiveEquipMiaoShu":280001629,"MaxUPgeade":50,"QiangHua":23,"MaxStar":3,"ExclusiveEquipStarAttr":3000000,"TeshuShuXingID":60035169,"TeshuJiNengFanYiID":0,"ExclusiveNinJas":45003,"WNType":0,"WNID":0,"ExchangeID":0,"ExchangeCostType":0,"ExchangeCostID":0,"ExchangeCostCount":0,"JiBanJiNengIcon":["JN_05_Kurumi"],"TeshuJiNengStar":[2],"TeshuJiNengID":[4505111],"CostType":[2,2,2,1],"CostID":[6056,6057,9511,76],"CostNum":[45,3,1,900]},{"_id":5170,"ExclusiveEquipId":5170,"ExclusiveEquipName":280000664,"ExclusiveEquipIcon":"ZSZB_Kuririn_01","TeshuShuXingIcon":"ZSZB_SX_01","Quality":7,"DangCi":8,"Property":4,"ExclusiveEquipMiaoShu":280001630,"MaxUPgeade":50,"QiangHua":23,"MaxStar":3,"ExclusiveEquipStarAttr":3000000,"TeshuShuXingID":60035170,"TeshuJiNengFanYiID":0,"ExclusiveNinJas":45103,"WNType":0,"WNID":0,"ExchangeID":0,"ExchangeCostType":0,"ExchangeCostID":0,"ExchangeCostCount":0,"JiBanJiNengIcon":["JN_05_SonGoku_bs"],"TeshuJiNengStar":[2],"TeshuJiNengID":[4515111],"CostType":[2,2,2,1],"CostID":[6056,6057,9511,76],"CostNum":[45,3,1,900]},{"_id":6101,"ExclusiveEquipId":6101,"ExclusiveEquipName":280000560,"ExclusiveEquipIcon":"ZSZB_Rider_02","TeshuShuXingIcon":"ZSZB_SX_02","Quality":9,"DangCi":5,"Property":1,"ExclusiveEquipMiaoShu":280001561,"MaxUPgeade":50,"QiangHua":32,"MaxStar":5,"ExclusiveEquipStarAttr":4000000,"TeshuShuXingID":60036101,"TeshuJiNengFanYiID":0,"ExclusiveNinJas":30703,"WNType":2,"WNID":13050,"ExchangeID":0,"ExchangeCostType":0,"ExchangeCostID":0,"ExchangeCostCount":0,"JiBanJiNengIcon":["JN_06_Rider"],"TeshuJiNengStar":[2],"TeshuJiNengID":[3075111],"CostType":[2,2,2,1],"CostID":[6056,6057,9511,76],"CostNum":[45,3,1,2700]},{"_id":6102,"ExclusiveEquipId":6102,"ExclusiveEquipName":280000562,"ExclusiveEquipIcon":"ZSZB_Nami_02","TeshuShuXingIcon":"ZSZB_SX_02","Quality":9,"DangCi":5,"Property":3,"ExclusiveEquipMiaoShu":280001562,"MaxUPgeade":50,"QiangHua":33,"MaxStar":5,"ExclusiveEquipStarAttr":4000000,"TeshuShuXingID":60036102,"TeshuJiNengFanYiID":0,"ExclusiveNinJas":31003,"WNType":2,"WNID":13050,"ExchangeID":0,"ExchangeCostType":0,"ExchangeCostID":0,"ExchangeCostCount":0,"JiBanJiNengIcon":["JN_06_Nami"],"TeshuJiNengStar":[2],"TeshuJiNengID":[3105111],"CostType":[2,2,2,1],"CostID":[6056,6057,9511,76],"CostNum":[45,3,1,2700]},{"_id":6103,"ExclusiveEquipId":6103,"ExclusiveEquipName":280000564,"ExclusiveEquipIcon":"ZSZB_Trunks_02","TeshuShuXingIcon":"ZSZB_SX_02","Quality":9,"DangCi":5,"Property":2,"ExclusiveEquipMiaoShu":280001563,"MaxUPgeade":50,"QiangHua":33,"MaxStar":5,"ExclusiveEquipStarAttr":4000000,"TeshuShuXingID":60036103,"TeshuJiNengFanYiID":0,"ExclusiveNinJas":31203,"WNType":2,"WNID":13050,"ExchangeID":0,"ExchangeCostType":0,"ExchangeCostID":0,"ExchangeCostCount":0,"JiBanJiNengIcon":["JN_06_Trunks"],"TeshuJiNengStar":[2],"TeshuJiNengID":[3125111],"CostType":[2,2,2,1],"CostID":[6056,6057,9511,76],"CostNum":[45,3,1,2700]},{"_id":6105,"ExclusiveEquipId":6105,"ExclusiveEquipName":280000568,"ExclusiveEquipIcon":"ZSZB_Tengen_02","TeshuShuXingIcon":"ZSZB_SX_02","Quality":9,"DangCi":6,"Property":3,"ExclusiveEquipMiaoShu":280001597,"MaxUPgeade":50,"QiangHua":31,"MaxStar":5,"ExclusiveEquipStarAttr":4000000,"TeshuShuXingID":60036105,"TeshuJiNengFanYiID":0,"ExclusiveNinJas":30103,"WNType":2,"WNID":13050,"ExchangeID":0,"ExchangeCostType":0,"ExchangeCostID":0,"ExchangeCostCount":0,"JiBanJiNengIcon":["JN_06_Tengen"],"TeshuJiNengStar":[2],"TeshuJiNengID":[3016111],"CostType":[2,2,2,1],"CostID":[6056,6057,9511,76],"CostNum":[45,3,1,2700]},{"_id":6106,"ExclusiveEquipId":6106,"ExclusiveEquipName":280000570,"ExclusiveEquipIcon":"ZSZB_Sakura_02","TeshuShuXingIcon":"ZSZB_SX_02","Quality":9,"DangCi":5,"Property":3,"ExclusiveEquipMiaoShu":280001566,"MaxUPgeade":50,"QiangHua":32,"MaxStar":5,"ExclusiveEquipStarAttr":4000000,"TeshuShuXingID":60036106,"TeshuJiNengFanYiID":0,"ExclusiveNinJas":30203,"WNType":2,"WNID":13050,"ExchangeID":0,"ExchangeCostType":0,"ExchangeCostID":0,"ExchangeCostCount":0,"JiBanJiNengIcon":["JN_06_Sakura"],"TeshuJiNengStar":[2],"TeshuJiNengID":[3026111],"CostType":[2,2,2,1],"CostID":[6056,6057,9511,76],"CostNum":[45,3,1,2700]},{"_id":6107,"ExclusiveEquipId":6107,"ExclusiveEquipName":280000572,"ExclusiveEquipIcon":"ZSZB_Naruto_02","TeshuShuXingIcon":"ZSZB_SX_02","Quality":9,"DangCi":5,"Property":3,"ExclusiveEquipMiaoShu":280001567,"MaxUPgeade":50,"QiangHua":33,"MaxStar":5,"ExclusiveEquipStarAttr":4000000,"TeshuShuXingID":60036107,"TeshuJiNengFanYiID":0,"ExclusiveNinJas":30303,"WNType":2,"WNID":13050,"ExchangeID":0,"ExchangeCostType":0,"ExchangeCostID":0,"ExchangeCostCount":0,"JiBanJiNengIcon":["JN_06_Naruto"],"TeshuJiNengStar":[2],"TeshuJiNengID":[3036111],"CostType":[2,2,2,1],"CostID":[6056,6057,9511,76],"CostNum":[45,3,1,2700]},{"_id":6108,"ExclusiveEquipId":6108,"ExclusiveEquipName":280000574,"ExclusiveEquipIcon":"ZSZB_Orihime_02","TeshuShuXingIcon":"ZSZB_SX_02","Quality":9,"DangCi":5,"Property":2,"ExclusiveEquipMiaoShu":280001568,"MaxUPgeade":50,"QiangHua":32,"MaxStar":5,"ExclusiveEquipStarAttr":4000000,"TeshuShuXingID":60036108,"TeshuJiNengFanYiID":0,"ExclusiveNinJas":30403,"WNType":2,"WNID":13050,"ExchangeID":0,"ExchangeCostType":0,"ExchangeCostID":0,"ExchangeCostCount":0,"JiBanJiNengIcon":["JN_06_Orihime"],"TeshuJiNengStar":[2],"TeshuJiNengID":[3046111],"CostType":[2,2,2,1],"CostID":[6056,6057,9511,76],"CostNum":[45,3,1,2700]},{"_id":6109,"ExclusiveEquipId":6109,"ExclusiveEquipName":280000576,"ExclusiveEquipIcon":"ZSZB_Cifer_02","TeshuShuXingIcon":"ZSZB_SX_02","Quality":9,"DangCi":5,"Property":1,"ExclusiveEquipMiaoShu":280001569,"MaxUPgeade":50,"QiangHua":33,"MaxStar":5,"ExclusiveEquipStarAttr":4000000,"TeshuShuXingID":60036109,"TeshuJiNengFanYiID":0,"ExclusiveNinJas":31703,"WNType":2,"WNID":13050,"ExchangeID":0,"ExchangeCostType":0,"ExchangeCostID":0,"ExchangeCostCount":0,"JiBanJiNengIcon":["JN_06_Cifer"],"TeshuJiNengStar":[2],"TeshuJiNengID":[3176111],"CostType":[2,2,2,1],"CostID":[6056,6057,9511,76],"CostNum":[45,3,1,2700]},{"_id":6112,"ExclusiveEquipId":6112,"ExclusiveEquipName":280000582,"ExclusiveEquipIcon":"ZSZB_Kirei_02","TeshuShuXingIcon":"ZSZB_SX_02","Quality":9,"DangCi":5,"Property":2,"ExclusiveEquipMiaoShu":280001572,"MaxUPgeade":50,"QiangHua":31,"MaxStar":5,"ExclusiveEquipStarAttr":4000000,"TeshuShuXingID":60036112,"TeshuJiNengFanYiID":0,"ExclusiveNinJas":31403,"WNType":2,"WNID":13050,"ExchangeID":0,"ExchangeCostType":0,"ExchangeCostID":0,"ExchangeCostCount":0,"JiBanJiNengIcon":["JN_06_Kirei"],"TeshuJiNengStar":[2],"TeshuJiNengID":[3145111],"CostType":[2,2,2,1],"CostID":[6056,6057,9511,76],"CostNum":[45,3,1,2700]},{"_id":6113,"ExclusiveEquipId":6113,"ExclusiveEquipName":280000647,"ExclusiveEquipIcon":"ZSZB_A_02","TeshuShuXingIcon":"ZSZB_SX_02","Quality":9,"DangCi":6,"Property":2,"ExclusiveEquipMiaoShu":280001613,"MaxUPgeade":50,"QiangHua":33,"MaxStar":5,"ExclusiveEquipStarAttr":4000000,"TeshuShuXingID":60036113,"TeshuJiNengFanYiID":0,"ExclusiveNinJas":30603,"WNType":2,"WNID":13050,"ExchangeID":0,"ExchangeCostType":0,"ExchangeCostID":0,"ExchangeCostCount":0,"JiBanJiNengIcon":["JN_06_A"],"TeshuJiNengStar":[2],"TeshuJiNengID":[3065111],"CostType":[2,2,2,1],"CostID":[6056,6057,9511,76],"CostNum":[45,3,1,2700]},{"_id":6115,"ExclusiveEquipId":6115,"ExclusiveEquipName":280000588,"ExclusiveEquipIcon":"ZSZB_Zoro_02","TeshuShuXingIcon":"ZSZB_SX_02","Quality":9,"DangCi":6,"Property":1,"ExclusiveEquipMiaoShu":280001575,"MaxUPgeade":50,"QiangHua":33,"MaxStar":5,"ExclusiveEquipStarAttr":4000000,"TeshuShuXingID":60036115,"TeshuJiNengFanYiID":0,"ExclusiveNinJas":30903,"WNType":2,"WNID":13050,"ExchangeID":0,"ExchangeCostType":0,"ExchangeCostID":0,"ExchangeCostCount":0,"JiBanJiNengIcon":["JN_06_Zoro"],"TeshuJiNengStar":[2],"TeshuJiNengID":[3095111],"CostType":[2,2,2,1],"CostID":[6056,6057,9511,76],"CostNum":[45,3,1,2700]},{"_id":6118,"ExclusiveEquipId":6118,"ExclusiveEquipName":280000594,"ExclusiveEquipIcon":"ZSZB_TodoAoi_02","TeshuShuXingIcon":"ZSZB_SX_02","Quality":9,"DangCi":5,"Property":1,"ExclusiveEquipMiaoShu":280001578,"MaxUPgeade":50,"QiangHua":31,"MaxStar":5,"ExclusiveEquipStarAttr":4000000,"TeshuShuXingID":60036118,"TeshuJiNengFanYiID":0,"ExclusiveNinJas":31603,"WNType":2,"WNID":13050,"ExchangeID":0,"ExchangeCostType":0,"ExchangeCostID":0,"ExchangeCostCount":0,"JiBanJiNengIcon":["JN_06_TodoAoi"],"TeshuJiNengStar":[2],"TeshuJiNengID":[3167111],"CostType":[2,2,2,1],"CostID":[6056,6057,9511,76],"CostNum":[45,3,1,2700]},{"_id":6119,"ExclusiveEquipId":6119,"ExclusiveEquipName":280000596,"ExclusiveEquipIcon":"ZSZB_Leafa_02","TeshuShuXingIcon":"ZSZB_SX_02","Quality":9,"DangCi":5,"Property":1,"ExclusiveEquipMiaoShu":280001579,"MaxUPgeade":50,"QiangHua":33,"MaxStar":5,"ExclusiveEquipStarAttr":4000000,"TeshuShuXingID":60036119,"TeshuJiNengFanYiID":0,"ExclusiveNinJas":31903,"WNType":2,"WNID":13050,"ExchangeID":0,"ExchangeCostType":0,"ExchangeCostID":0,"ExchangeCostCount":0,"JiBanJiNengIcon":["JN_06_Leafa"],"TeshuJiNengStar":[2],"TeshuJiNengID":[3197111],"CostType":[2,2,2,1],"CostID":[6056,6057,9511,76],"CostNum":[45,3,1,2700]},{"_id":6120,"ExclusiveEquipId":6120,"ExclusiveEquipName":280000598,"ExclusiveEquipIcon":"ZSZB_Itachi_02","TeshuShuXingIcon":"ZSZB_SX_02","Quality":9,"DangCi":7,"Property":5,"ExclusiveEquipMiaoShu":280001580,"MaxUPgeade":50,"QiangHua":33,"MaxStar":5,"ExclusiveEquipStarAttr":4000000,"TeshuShuXingID":60036120,"TeshuJiNengFanYiID":0,"ExclusiveNinJas":40103,"WNType":2,"WNID":13051,"ExchangeID":0,"ExchangeCostType":0,"ExchangeCostID":0,"ExchangeCostCount":0,"JiBanJiNengIcon":["JN_06_Itachi"],"TeshuJiNengStar":[2],"TeshuJiNengID":[4015111],"CostType":[2,2,2,1],"CostID":[6056,6057,9511,76],"CostNum":[45,3,1,2700]},{"_id":6121,"ExclusiveEquipId":6121,"ExclusiveEquipName":280000600,"ExclusiveEquipIcon":"ZSZB_Ace_02","TeshuShuXingIcon":"ZSZB_SX_02","Quality":9,"DangCi":6,"Property":3,"ExclusiveEquipMiaoShu":280001581,"MaxUPgeade":50,"QiangHua":33,"MaxStar":5,"ExclusiveEquipStarAttr":4000000,"TeshuShuXingID":60036121,"TeshuJiNengFanYiID":0,"ExclusiveNinJas":40203,"WNType":2,"WNID":13050,"ExchangeID":0,"ExchangeCostType":0,"ExchangeCostID":0,"ExchangeCostCount":0,"JiBanJiNengIcon":["JN_06_Ace"],"TeshuJiNengStar":[2],"TeshuJiNengID":[4025111],"CostType":[2,2,2,1],"CostID":[6056,6057,9511,76],"CostNum":[45,3,1,2700]},{"_id":6122,"ExclusiveEquipId":6122,"ExclusiveEquipName":280000602,"ExclusiveEquipIcon":"ZSZB_Vegeta_02","TeshuShuXingIcon":"ZSZB_SX_02","Quality":9,"DangCi":7,"Property":5,"ExclusiveEquipMiaoShu":280001582,"MaxUPgeade":50,"QiangHua":33,"MaxStar":5,"ExclusiveEquipStarAttr":4000000,"TeshuShuXingID":60036122,"TeshuJiNengFanYiID":0,"ExclusiveNinJas":40303,"WNType":2,"WNID":13051,"ExchangeID":0,"ExchangeCostType":0,"ExchangeCostID":0,"ExchangeCostCount":0,"JiBanJiNengIcon":["JN_06_Vegeta"],"TeshuJiNengStar":[2],"TeshuJiNengID":[4035111],"CostType":[2,2,2,1],"CostID":[6056,6057,9511,76],"CostNum":[45,3,1,2700]},{"_id":6123,"ExclusiveEquipId":6123,"ExclusiveEquipName":280000604,"ExclusiveEquipIcon":"ZSZB_Asuna_02","TeshuShuXingIcon":"ZSZB_SX_02","Quality":9,"DangCi":7,"Property":4,"ExclusiveEquipMiaoShu":280001583,"MaxUPgeade":50,"QiangHua":32,"MaxStar":5,"ExclusiveEquipStarAttr":4000000,"TeshuShuXingID":60036123,"TeshuJiNengFanYiID":0,"ExclusiveNinJas":40403,"WNType":2,"WNID":13051,"ExchangeID":0,"ExchangeCostType":0,"ExchangeCostID":0,"ExchangeCostCount":0,"JiBanJiNengIcon":["JN_06_Asuna"],"TeshuJiNengStar":[2],"TeshuJiNengID":[4045111],"CostType":[2,2,2,1],"CostID":[6056,6057,9511,76],"CostNum":[45,3,1,2700]},{"_id":6124,"ExclusiveEquipId":6124,"ExclusiveEquipName":280000606,"ExclusiveEquipIcon":"ZSZB_Kakashi_Kamui02","TeshuShuXingIcon":"ZSZB_SX_02","Quality":9,"DangCi":7,"Property":5,"ExclusiveEquipMiaoShu":280001584,"MaxUPgeade":50,"QiangHua":33,"MaxStar":5,"ExclusiveEquipStarAttr":4000000,"TeshuShuXingID":60036124,"TeshuJiNengFanYiID":0,"ExclusiveNinJas":40503,"WNType":2,"WNID":13051,"ExchangeID":0,"ExchangeCostType":0,"ExchangeCostID":0,"ExchangeCostCount":0,"JiBanJiNengIcon":["JN_06_Kakashi_Kamui"],"TeshuJiNengStar":[2],"TeshuJiNengID":[4055111],"CostType":[2,2,2,1],"CostID":[6056,6057,9511,76],"CostNum":[45,3,1,2700]},{"_id":6125,"ExclusiveEquipId":6125,"ExclusiveEquipName":280000608,"ExclusiveEquipIcon":"ZSZB_Kyo_02","TeshuShuXingIcon":"ZSZB_SX_02","Quality":9,"DangCi":7,"Property":4,"ExclusiveEquipMiaoShu":280001585,"MaxUPgeade":50,"QiangHua":33,"MaxStar":5,"ExclusiveEquipStarAttr":4000000,"TeshuShuXingID":60036125,"TeshuJiNengFanYiID":0,"ExclusiveNinJas":40603,"WNType":2,"WNID":13051,"ExchangeID":0,"ExchangeCostType":0,"ExchangeCostID":0,"ExchangeCostCount":0,"JiBanJiNengIcon":["JN_06_Kyo"],"TeshuJiNengStar":[2],"TeshuJiNengID":[4065111],"CostType":[2,2,2,1],"CostID":[6056,6057,9511,76],"CostNum":[45,3,1,2700]},{"_id":6126,"ExclusiveEquipId":6126,"ExclusiveEquipName":280000610,"ExclusiveEquipIcon":"ZSZB_Hancock_02","TeshuShuXingIcon":"ZSZB_SX_02","Quality":9,"DangCi":7,"Property":5,"ExclusiveEquipMiaoShu":280001586,"MaxUPgeade":50,"QiangHua":32,"MaxStar":5,"ExclusiveEquipStarAttr":4000000,"TeshuShuXingID":60036126,"TeshuJiNengFanYiID":0,"ExclusiveNinJas":40703,"WNType":2,"WNID":13051,"ExchangeID":0,"ExchangeCostType":0,"ExchangeCostID":0,"ExchangeCostCount":0,"JiBanJiNengIcon":["JN_06_Hancock"],"TeshuJiNengStar":[2],"TeshuJiNengID":[4075111],"CostType":[2,2,2,1],"CostID":[6056,6057,9511,76],"CostNum":[45,3,1,2700]},{"_id":6127,"ExclusiveEquipId":6127,"ExclusiveEquipName":280000612,"ExclusiveEquipIcon":"ZSZB_Emiya_02","TeshuShuXingIcon":"ZSZB_SX_02","Quality":9,"DangCi":7,"Property":4,"ExclusiveEquipMiaoShu":280001587,"MaxUPgeade":50,"QiangHua":31,"MaxStar":5,"ExclusiveEquipStarAttr":4000000,"TeshuShuXingID":60036127,"TeshuJiNengFanYiID":0,"ExclusiveNinJas":40803,"WNType":2,"WNID":13051,"ExchangeID":0,"ExchangeCostType":0,"ExchangeCostID":0,"ExchangeCostCount":0,"JiBanJiNengIcon":["JN_06_Emiya"],"TeshuJiNengStar":[2],"TeshuJiNengID":[4085111],"CostType":[2,2,2,1],"CostID":[6056,6057,9511,76],"CostNum":[45,3,1,2700]},{"_id":6128,"ExclusiveEquipId":6128,"ExclusiveEquipName":280000614,"ExclusiveEquipIcon":"ZSZB_Aizen_02","TeshuShuXingIcon":"ZSZB_SX_02","Quality":9,"DangCi":6,"Property":2,"ExclusiveEquipMiaoShu":280001588,"MaxUPgeade":50,"QiangHua":33,"MaxStar":5,"ExclusiveEquipStarAttr":4000000,"TeshuShuXingID":60036128,"TeshuJiNengFanYiID":0,"ExclusiveNinJas":40903,"WNType":2,"WNID":13050,"ExchangeID":0,"ExchangeCostType":0,"ExchangeCostID":0,"ExchangeCostCount":0,"JiBanJiNengIcon":["JN_06_Aizen"],"TeshuJiNengStar":[2],"TeshuJiNengID":[4095111],"CostType":[2,2,2,1],"CostID":[6056,6057,9511,76],"CostNum":[45,3,1,2700]},{"_id":6129,"ExclusiveEquipId":6129,"ExclusiveEquipName":280000616,"ExclusiveEquipIcon":"ZSZB_Megumi_02","TeshuShuXingIcon":"ZSZB_SX_02","Quality":9,"DangCi":6,"Property":1,"ExclusiveEquipMiaoShu":280001589,"MaxUPgeade":50,"QiangHua":33,"MaxStar":5,"ExclusiveEquipStarAttr":4000000,"TeshuShuXingID":60036129,"TeshuJiNengFanYiID":0,"ExclusiveNinJas":41003,"WNType":2,"WNID":13050,"ExchangeID":0,"ExchangeCostType":0,"ExchangeCostID":0,"ExchangeCostCount":0,"JiBanJiNengIcon":["JN_06_Megumi"],"TeshuJiNengStar":[2],"TeshuJiNengID":[4105111],"CostType":[2,2,2,1],"CostID":[6056,6057,9511,76],"CostNum":[45,3,1,2700]},{"_id":6130,"ExclusiveEquipId":6130,"ExclusiveEquipName":280000618,"ExclusiveEquipIcon":"ZSZB_Cell_02","TeshuShuXingIcon":"ZSZB_SX_02","Quality":9,"DangCi":6,"Property":3,"ExclusiveEquipMiaoShu":280001590,"MaxUPgeade":50,"QiangHua":33,"MaxStar":5,"ExclusiveEquipStarAttr":4000000,"TeshuShuXingID":60036130,"TeshuJiNengFanYiID":0,"ExclusiveNinJas":41103,"WNType":2,"WNID":13050,"ExchangeID":0,"ExchangeCostType":0,"ExchangeCostID":0,"ExchangeCostCount":0,"JiBanJiNengIcon":["JN_06_Cell"],"TeshuJiNengStar":[2],"TeshuJiNengID":[4115111],"CostType":[2,2,2,1],"CostID":[6056,6057,9511,76],"CostNum":[45,3,1,2700]},{"_id":6131,"ExclusiveEquipId":6131,"ExclusiveEquipName":280000620,"ExclusiveEquipIcon":"ZSZB_Tsunade_02","TeshuShuXingIcon":"ZSZB_SX_02","Quality":9,"DangCi":6,"Property":2,"ExclusiveEquipMiaoShu":280001591,"MaxUPgeade":50,"QiangHua":33,"MaxStar":5,"ExclusiveEquipStarAttr":4000000,"TeshuShuXingID":60036131,"TeshuJiNengFanYiID":0,"ExclusiveNinJas":41203,"WNType":2,"WNID":13050,"ExchangeID":0,"ExchangeCostType":0,"ExchangeCostID":0,"ExchangeCostCount":0,"JiBanJiNengIcon":["JN_06_Tsunade"],"TeshuJiNengStar":[2],"TeshuJiNengID":[4125111],"CostType":[2,2,2,1],"CostID":[6056,6057,9511,76],"CostNum":[45,3,1,2700]},{"_id":6132,"ExclusiveEquipId":6132,"ExclusiveEquipName":280000622,"ExclusiveEquipIcon":"ZSZB_Yuta_02","TeshuShuXingIcon":"ZSZB_SX_02","Quality":9,"DangCi":6,"Property":1,"ExclusiveEquipMiaoShu":280001592,"MaxUPgeade":50,"QiangHua":32,"MaxStar":5,"ExclusiveEquipStarAttr":4000000,"TeshuShuXingID":60036132,"TeshuJiNengFanYiID":0,"ExclusiveNinJas":41303,"WNType":2,"WNID":13050,"ExchangeID":0,"ExchangeCostType":0,"ExchangeCostID":0,"ExchangeCostCount":0,"JiBanJiNengIcon":["JN_06_Yuta"],"TeshuJiNengStar":[2],"TeshuJiNengID":[4135111],"CostType":[2,2,2,1],"CostID":[6056,6057,9511,76],"CostNum":[45,3,1,2700]},{"_id":6133,"ExclusiveEquipId":6133,"ExclusiveEquipName":280000624,"ExclusiveEquipIcon":"ZSZB_Frieza_02","TeshuShuXingIcon":"ZSZB_SX_02","Quality":9,"DangCi":6,"Property":2,"ExclusiveEquipMiaoShu":280001593,"MaxUPgeade":50,"QiangHua":33,"MaxStar":5,"ExclusiveEquipStarAttr":4000000,"TeshuShuXingID":60036133,"TeshuJiNengFanYiID":0,"ExclusiveNinJas":41403,"WNType":2,"WNID":13050,"ExchangeID":0,"ExchangeCostType":0,"ExchangeCostID":0,"ExchangeCostCount":0,"JiBanJiNengIcon":["JN_06_Frieza"],"TeshuJiNengStar":[2],"TeshuJiNengID":[4145111],"CostType":[2,2,2,1],"CostID":[6056,6057,9511,76],"CostNum":[45,3,1,2700]},{"_id":6134,"ExclusiveEquipId":6134,"ExclusiveEquipName":280000626,"ExclusiveEquipIcon":"ZSZB_Chopper_02","TeshuShuXingIcon":"ZSZB_SX_02","Quality":9,"DangCi":6,"Property":2,"ExclusiveEquipMiaoShu":280001594,"MaxUPgeade":50,"QiangHua":32,"MaxStar":5,"ExclusiveEquipStarAttr":4000000,"TeshuShuXingID":60036134,"TeshuJiNengFanYiID":0,"ExclusiveNinJas":41503,"WNType":2,"WNID":13050,"ExchangeID":0,"ExchangeCostType":0,"ExchangeCostID":0,"ExchangeCostCount":0,"JiBanJiNengIcon":["JN_06_Chopper"],"TeshuJiNengStar":[2],"TeshuJiNengID":[4155111],"CostType":[2,2,2,1],"CostID":[6056,6057,9511,76],"CostNum":[45,3,1,2700]},{"_id":6135,"ExclusiveEquipId":6135,"ExclusiveEquipName":280000628,"ExclusiveEquipIcon":"ZSZB_Ichigo_02","TeshuShuXingIcon":"ZSZB_SX_02","Quality":9,"DangCi":7,"Property":5,"ExclusiveEquipMiaoShu":280001595,"MaxUPgeade":50,"QiangHua":33,"MaxStar":5,"ExclusiveEquipStarAttr":4000000,"TeshuShuXingID":60036135,"TeshuJiNengFanYiID":0,"ExclusiveNinJas":41603,"WNType":2,"WNID":13051,"ExchangeID":0,"ExchangeCostType":0,"ExchangeCostID":0,"ExchangeCostCount":0,"JiBanJiNengIcon":["JN_06_Ichigo"],"TeshuJiNengStar":[2],"TeshuJiNengID":[4165111],"CostType":[2,2,2,1],"CostID":[6056,6057,9511,76],"CostNum":[45,3,1,2700]},{"_id":6136,"ExclusiveEquipId":6136,"ExclusiveEquipName":280000630,"ExclusiveEquipIcon":"ZSZB_SonGoKu_02","TeshuShuXingIcon":"ZSZB_SX_02","Quality":9,"DangCi":7,"Property":4,"ExclusiveEquipMiaoShu":280001596,"MaxUPgeade":50,"QiangHua":33,"MaxStar":5,"ExclusiveEquipStarAttr":4000000,"TeshuShuXingID":60036136,"TeshuJiNengFanYiID":0,"ExclusiveNinJas":41703,"WNType":2,"WNID":13051,"ExchangeID":0,"ExchangeCostType":0,"ExchangeCostID":0,"ExchangeCostCount":0,"JiBanJiNengIcon":["JN_06_SonGoKu"],"TeshuJiNengStar":[2],"TeshuJiNengID":[4175111],"CostType":[2,2,2,1],"CostID":[6056,6057,9511,76],"CostNum":[45,3,1,2700]},{"_id":6137,"ExclusiveEquipId":6137,"ExclusiveEquipName":280000631,"ExclusiveEquipIcon":"ZSZB_Yuji_02","TeshuShuXingIcon":"ZSZB_SX_02","Quality":9,"DangCi":6,"Property":3,"ExclusiveEquipMiaoShu":280001565,"MaxUPgeade":50,"QiangHua":33,"MaxStar":5,"ExclusiveEquipStarAttr":4000000,"TeshuShuXingID":60036137,"TeshuJiNengFanYiID":0,"ExclusiveNinJas":32003,"WNType":2,"WNID":13050,"ExchangeID":0,"ExchangeCostType":0,"ExchangeCostID":0,"ExchangeCostCount":0,"JiBanJiNengIcon":["JN_06_Yuji"],"TeshuJiNengStar":[2],"TeshuJiNengID":[3205111],"CostType":[2,2,2,1],"CostID":[6056,6057,9511,76],"CostNum":[45,3,1,2700]},{"_id":6138,"ExclusiveEquipId":6138,"ExclusiveEquipName":280000632,"ExclusiveEquipIcon":"ZSZB_Nezuko_02","TeshuShuXingIcon":"ZSZB_SX_02","Quality":9,"DangCi":7,"Property":5,"ExclusiveEquipMiaoShu":280001598,"MaxUPgeade":50,"QiangHua":31,"MaxStar":5,"ExclusiveEquipStarAttr":4000000,"TeshuShuXingID":60036138,"TeshuJiNengFanYiID":0,"ExclusiveNinJas":41803,"WNType":2,"WNID":13051,"ExchangeID":0,"ExchangeCostType":0,"ExchangeCostID":0,"ExchangeCostCount":0,"JiBanJiNengIcon":["JN_06_Nezuko"],"TeshuJiNengStar":[2],"TeshuJiNengID":[4185111],"CostType":[2,2,2,1],"CostID":[6056,6057,9511,76],"CostNum":[45,3,1,2700]},{"_id":6139,"ExclusiveEquipId":6139,"ExclusiveEquipName":280000633,"ExclusiveEquipIcon":"ZSZB_Gintoki_02","TeshuShuXingIcon":"ZSZB_SX_02","Quality":9,"DangCi":6,"Property":1,"ExclusiveEquipMiaoShu":280001599,"MaxUPgeade":50,"QiangHua":31,"MaxStar":5,"ExclusiveEquipStarAttr":4000000,"TeshuShuXingID":60036139,"TeshuJiNengFanYiID":0,"ExclusiveNinJas":41903,"WNType":2,"WNID":13050,"ExchangeID":0,"ExchangeCostType":0,"ExchangeCostID":0,"ExchangeCostCount":0,"JiBanJiNengIcon":["JN_06_Gintoki"],"TeshuJiNengStar":[2],"TeshuJiNengID":[4195111],"CostType":[2,2,2,1],"CostID":[6056,6057,9511,76],"CostNum":[45,3,1,2700]},{"_id":6140,"ExclusiveEquipId":6140,"ExclusiveEquipName":280000634,"ExclusiveEquipIcon":"ZSZB_Athena_02","TeshuShuXingIcon":"ZSZB_SX_02","Quality":9,"DangCi":7,"Property":4,"ExclusiveEquipMiaoShu":280001600,"MaxUPgeade":50,"QiangHua":32,"MaxStar":5,"ExclusiveEquipStarAttr":4000000,"TeshuShuXingID":60036140,"TeshuJiNengFanYiID":0,"ExclusiveNinJas":42003,"WNType":2,"WNID":13051,"ExchangeID":0,"ExchangeCostType":0,"ExchangeCostID":0,"ExchangeCostCount":0,"JiBanJiNengIcon":["JN_06_Athena"],"TeshuJiNengStar":[2],"TeshuJiNengID":[4205111],"CostType":[2,2,2,1],"CostID":[6056,6057,9511,76],"CostNum":[45,3,1,2700]},{"_id":6141,"ExclusiveEquipId":6141,"ExclusiveEquipName":280000635,"ExclusiveEquipIcon":"ZSZB_Levi_02","TeshuShuXingIcon":"ZSZB_SX_02","Quality":9,"DangCi":6,"Property":3,"ExclusiveEquipMiaoShu":280001601,"MaxUPgeade":50,"QiangHua":33,"MaxStar":5,"ExclusiveEquipStarAttr":4000000,"TeshuShuXingID":60036141,"TeshuJiNengFanYiID":0,"ExclusiveNinJas":42103,"WNType":2,"WNID":13050,"ExchangeID":0,"ExchangeCostType":0,"ExchangeCostID":0,"ExchangeCostCount":0,"JiBanJiNengIcon":["JN_06_Levi"],"TeshuJiNengStar":[2],"TeshuJiNengID":[4215111],"CostType":[2,2,2,1],"CostID":[6056,6057,9511,76],"CostNum":[45,3,1,2700]},{"_id":6142,"ExclusiveEquipId":6142,"ExclusiveEquipName":280000636,"ExclusiveEquipIcon":"ZSZB_Killua_02","TeshuShuXingIcon":"ZSZB_SX_02","Quality":9,"DangCi":6,"Property":1,"ExclusiveEquipMiaoShu":280001602,"MaxUPgeade":50,"QiangHua":33,"MaxStar":5,"ExclusiveEquipStarAttr":4000000,"TeshuShuXingID":60036142,"TeshuJiNengFanYiID":0,"ExclusiveNinJas":43503,"WNType":2,"WNID":13050,"ExchangeID":0,"ExchangeCostType":0,"ExchangeCostID":0,"ExchangeCostCount":0,"JiBanJiNengIcon":["JN_06_Killua"],"TeshuJiNengStar":[2],"TeshuJiNengID":[4355111],"CostType":[2,2,2,1],"CostID":[6056,6057,9511,76],"CostNum":[45,3,1,2700]},{"_id":6143,"ExclusiveEquipId":6143,"ExclusiveEquipName":280000637,"ExclusiveEquipIcon":"ZSZB_Shino_02","TeshuShuXingIcon":"ZSZB_SX_02","Quality":9,"DangCi":6,"Property":3,"ExclusiveEquipMiaoShu":280001603,"MaxUPgeade":50,"QiangHua":33,"MaxStar":5,"ExclusiveEquipStarAttr":4000000,"TeshuShuXingID":60036143,"TeshuJiNengFanYiID":0,"ExclusiveNinJas":42203,"WNType":2,"WNID":13050,"ExchangeID":0,"ExchangeCostType":0,"ExchangeCostID":0,"ExchangeCostCount":0,"JiBanJiNengIcon":["JN_06_Shino"],"TeshuJiNengStar":[2],"TeshuJiNengID":[4225111],"CostType":[2,2,2,1],"CostID":[6056,6057,9511,76],"CostNum":[45,3,1,2700]},{"_id":6144,"ExclusiveEquipId":6144,"ExclusiveEquipName":280000638,"ExclusiveEquipIcon":"ZSZB_Kyoujurou_02","TeshuShuXingIcon":"ZSZB_SX_02","Quality":9,"DangCi":7,"Property":4,"ExclusiveEquipMiaoShu":280001604,"MaxUPgeade":50,"QiangHua":41,"MaxStar":5,"ExclusiveEquipStarAttr":4001000,"TeshuShuXingID":60036144,"TeshuJiNengFanYiID":0,"ExclusiveNinJas":42303,"WNType":2,"WNID":13051,"ExchangeID":0,"ExchangeCostType":0,"ExchangeCostID":0,"ExchangeCostCount":0,"JiBanJiNengIcon":["JN_06_Kyoujurou"],"TeshuJiNengStar":[2],"TeshuJiNengID":[4235111],"CostType":[2,2,2,1],"CostID":[6056,6057,9511,76],"CostNum":[45,3,1,2700]},{"_id":6145,"ExclusiveEquipId":6145,"ExclusiveEquipName":280000639,"ExclusiveEquipIcon":"ZSZB_Shiryu_02","TeshuShuXingIcon":"ZSZB_SX_02","Quality":9,"DangCi":6,"Property":2,"ExclusiveEquipMiaoShu":280001605,"MaxUPgeade":50,"QiangHua":31,"MaxStar":5,"ExclusiveEquipStarAttr":4000000,"TeshuShuXingID":60036145,"TeshuJiNengFanYiID":0,"ExclusiveNinJas":42403,"WNType":2,"WNID":13050,"ExchangeID":0,"ExchangeCostType":0,"ExchangeCostID":0,"ExchangeCostCount":0,"JiBanJiNengIcon":["JN_06_Shiryu"],"TeshuJiNengStar":[2],"TeshuJiNengID":[4245111],"CostType":[2,2,2,1],"CostID":[6056,6057,9511,76],"CostNum":[45,3,1,2700]},{"_id":6146,"ExclusiveEquipId":6146,"ExclusiveEquipName":280000640,"ExclusiveEquipIcon":"ZSZB_Natsu_02","TeshuShuXingIcon":"ZSZB_SX_02","Quality":9,"DangCi":8,"Property":5,"ExclusiveEquipMiaoShu":280001606,"MaxUPgeade":50,"QiangHua":43,"MaxStar":5,"ExclusiveEquipStarAttr":4001000,"TeshuShuXingID":60036146,"TeshuJiNengFanYiID":0,"ExclusiveNinJas":42503,"WNType":2,"WNID":13052,"ExchangeID":0,"ExchangeCostType":0,"ExchangeCostID":0,"ExchangeCostCount":0,"JiBanJiNengIcon":["JN_06_Natsu"],"TeshuJiNengStar":[2],"TeshuJiNengID":[4255111],"CostType":[2,2,2,1],"CostID":[6056,6057,9511,76],"CostNum":[45,3,1,2700]},{"_id":6147,"ExclusiveEquipId":6147,"ExclusiveEquipName":280000641,"ExclusiveEquipIcon":"ZSZB_RoyMustang_02","TeshuShuXingIcon":"ZSZB_SX_02","Quality":9,"DangCi":7,"Property":5,"ExclusiveEquipMiaoShu":280001607,"MaxUPgeade":50,"QiangHua":42,"MaxStar":5,"ExclusiveEquipStarAttr":4001000,"TeshuShuXingID":60036147,"TeshuJiNengFanYiID":0,"ExclusiveNinJas":42603,"WNType":2,"WNID":13051,"ExchangeID":0,"ExchangeCostType":0,"ExchangeCostID":0,"ExchangeCostCount":0,"JiBanJiNengIcon":["JN_06_RoyMustang"],"TeshuJiNengStar":[2],"TeshuJiNengID":[4265111],"CostType":[2,2,2,1],"CostID":[6056,6057,9511,76],"CostNum":[45,3,1,2700]},{"_id":6148,"ExclusiveEquipId":6148,"ExclusiveEquipName":280000642,"ExclusiveEquipIcon":"ZSZB_Kurama_02","TeshuShuXingIcon":"ZSZB_SX_02","Quality":9,"DangCi":6,"Property":1,"ExclusiveEquipMiaoShu":280001608,"MaxUPgeade":50,"QiangHua":33,"MaxStar":5,"ExclusiveEquipStarAttr":4000000,"TeshuShuXingID":60036148,"TeshuJiNengFanYiID":0,"ExclusiveNinJas":42703,"WNType":2,"WNID":13050,"ExchangeID":0,"ExchangeCostType":0,"ExchangeCostID":0,"ExchangeCostCount":0,"JiBanJiNengIcon":["JN_06_Kurama"],"TeshuJiNengStar":[2],"TeshuJiNengID":[4275111],"CostType":[2,2,2,1],"CostID":[6056,6057,9511,76],"CostNum":[45,3,1,2700]},{"_id":6149,"ExclusiveEquipId":6149,"ExclusiveEquipName":280000643,"ExclusiveEquipIcon":"ZSZB_Rem_02","TeshuShuXingIcon":"ZSZB_SX_02","Quality":9,"DangCi":7,"Property":7,"ExclusiveEquipMiaoShu":280001609,"MaxUPgeade":50,"QiangHua":42,"MaxStar":5,"ExclusiveEquipStarAttr":4000000,"TeshuShuXingID":60036149,"TeshuJiNengFanYiID":0,"ExclusiveNinJas":42803,"WNType":2,"WNID":13052,"ExchangeID":0,"ExchangeCostType":0,"ExchangeCostID":0,"ExchangeCostCount":0,"JiBanJiNengIcon":["JN_06_Rem"],"TeshuJiNengStar":[2],"TeshuJiNengID":[4285111],"CostType":[2,2,2,1],"CostID":[6056,6057,9511,76],"CostNum":[45,3,1,2700]},{"_id":6150,"ExclusiveEquipId":6150,"ExclusiveEquipName":280000644,"ExclusiveEquipIcon":"ZSZB_Misaka_02","TeshuShuXingIcon":"ZSZB_SX_02","Quality":9,"DangCi":8,"Property":4,"ExclusiveEquipMiaoShu":280001610,"MaxUPgeade":50,"QiangHua":43,"MaxStar":5,"ExclusiveEquipStarAttr":4001000,"TeshuShuXingID":60036150,"TeshuJiNengFanYiID":0,"ExclusiveNinJas":42903,"WNType":2,"WNID":13052,"ExchangeID":0,"ExchangeCostType":0,"ExchangeCostID":0,"ExchangeCostCount":0,"JiBanJiNengIcon":["JN_06_Misaka"],"TeshuJiNengStar":[2],"TeshuJiNengID":[4295111],"CostType":[2,2,2,1],"CostID":[6056,6057,9511,76],"CostNum":[45,3,1,2700]},{"_id":6151,"ExclusiveEquipId":6151,"ExclusiveEquipName":280000645,"ExclusiveEquipIcon":"ZSZB_Pain_02","TeshuShuXingIcon":"ZSZB_SX_02","Quality":9,"DangCi":8,"Property":5,"ExclusiveEquipMiaoShu":280001611,"MaxUPgeade":50,"QiangHua":43,"MaxStar":5,"ExclusiveEquipStarAttr":4001000,"TeshuShuXingID":60036151,"TeshuJiNengFanYiID":0,"ExclusiveNinJas":43003,"WNType":2,"WNID":13052,"ExchangeID":0,"ExchangeCostType":0,"ExchangeCostID":0,"ExchangeCostCount":0,"JiBanJiNengIcon":["JN_06_Pain"],"TeshuJiNengStar":[2],"TeshuJiNengID":[4305111],"CostType":[2,2,2,1],"CostID":[6056,6057,9511,76],"CostNum":[45,3,1,2700]},{"_id":6152,"ExclusiveEquipId":6152,"ExclusiveEquipName":280000646,"ExclusiveEquipIcon":"ZSZB_Edward_02","TeshuShuXingIcon":"ZSZB_SX_02","Quality":9,"DangCi":8,"Property":4,"ExclusiveEquipMiaoShu":280001612,"MaxUPgeade":50,"QiangHua":41,"MaxStar":5,"ExclusiveEquipStarAttr":4001000,"TeshuShuXingID":60036152,"TeshuJiNengFanYiID":0,"ExclusiveNinJas":43103,"WNType":2,"WNID":13052,"ExchangeID":0,"ExchangeCostType":0,"ExchangeCostID":0,"ExchangeCostCount":0,"JiBanJiNengIcon":["JN_06_Edward"],"TeshuJiNengStar":[2],"TeshuJiNengID":[4315111],"CostType":[2,2,2,1],"CostID":[6056,6057,9511,76],"CostNum":[45,3,1,2700]},{"_id":6154,"ExclusiveEquipId":6154,"ExclusiveEquipName":280000648,"ExclusiveEquipIcon":"ZSZB_Saber_02","TeshuShuXingIcon":"ZSZB_SX_02","Quality":9,"DangCi":8,"Property":4,"ExclusiveEquipMiaoShu":280001614,"MaxUPgeade":50,"QiangHua":43,"MaxStar":5,"ExclusiveEquipStarAttr":4001000,"TeshuShuXingID":60036154,"TeshuJiNengFanYiID":0,"ExclusiveNinJas":43403,"WNType":2,"WNID":13052,"ExchangeID":0,"ExchangeCostType":0,"ExchangeCostID":0,"ExchangeCostCount":0,"JiBanJiNengIcon":["JN_06_Saber"],"TeshuJiNengStar":[2],"TeshuJiNengID":[4345111],"CostType":[2,2,2,1],"CostID":[6056,6057,9511,76],"CostNum":[45,3,1,2700]},{"_id":6155,"ExclusiveEquipId":6155,"ExclusiveEquipName":280000649,"ExclusiveEquipIcon":"ZSZB_Gojo_02","TeshuShuXingIcon":"ZSZB_SX_02","Quality":9,"DangCi":8,"Property":5,"ExclusiveEquipMiaoShu":280001615,"MaxUPgeade":50,"QiangHua":43,"MaxStar":5,"ExclusiveEquipStarAttr":4001000,"TeshuShuXingID":60036155,"TeshuJiNengFanYiID":0,"ExclusiveNinJas":43603,"WNType":2,"WNID":13052,"ExchangeID":0,"ExchangeCostType":0,"ExchangeCostID":0,"ExchangeCostCount":0,"JiBanJiNengIcon":["JN_06_Gojo"],"TeshuJiNengStar":[2],"TeshuJiNengID":[4365111],"CostType":[2,2,2,1],"CostID":[6056,6057,9511,76],"CostNum":[45,3,1,2700]},{"_id":6156,"ExclusiveEquipId":6156,"ExclusiveEquipName":280000650,"ExclusiveEquipIcon":"ZSZB_Josuke_02","TeshuShuXingIcon":"ZSZB_SX_02","Quality":9,"DangCi":8,"Property":4,"ExclusiveEquipMiaoShu":280001616,"MaxUPgeade":50,"QiangHua":42,"MaxStar":5,"ExclusiveEquipStarAttr":4001000,"TeshuShuXingID":60036156,"TeshuJiNengFanYiID":0,"ExclusiveNinJas":43703,"WNType":2,"WNID":13052,"ExchangeID":0,"ExchangeCostType":0,"ExchangeCostID":0,"ExchangeCostCount":0,"JiBanJiNengIcon":["JN_06_Josuke"],"TeshuJiNengStar":[2],"TeshuJiNengID":[4375111],"CostType":[2,2,2,1],"CostID":[6056,6057,9511,76],"CostNum":[45,3,1,2700]},{"_id":6157,"ExclusiveEquipId":6157,"ExclusiveEquipName":280000651,"ExclusiveEquipIcon":"ZSZB_Fern_02","TeshuShuXingIcon":"ZSZB_SX_02","Quality":9,"DangCi":8,"Property":7,"ExclusiveEquipMiaoShu":280001617,"MaxUPgeade":50,"QiangHua":43,"MaxStar":5,"ExclusiveEquipStarAttr":4001000,"TeshuShuXingID":60036157,"TeshuJiNengFanYiID":0,"ExclusiveNinJas":43803,"WNType":2,"WNID":13052,"ExchangeID":0,"ExchangeCostType":0,"ExchangeCostID":0,"ExchangeCostCount":0,"JiBanJiNengIcon":["JN_06_Fern"],"TeshuJiNengStar":[2],"TeshuJiNengID":[4385111],"CostType":[2,2,2,1],"CostID":[6056,6057,9511,76],"CostNum":[45,3,1,2700]},{"_id":6158,"ExclusiveEquipId":6158,"ExclusiveEquipName":280000652,"ExclusiveEquipIcon":"ZSZB_Kazuto_02","TeshuShuXingIcon":"ZSZB_SX_02","Quality":9,"DangCi":8,"Property":5,"ExclusiveEquipMiaoShu":280001618,"MaxUPgeade":50,"QiangHua":43,"MaxStar":5,"ExclusiveEquipStarAttr":4001000,"TeshuShuXingID":60036158,"TeshuJiNengFanYiID":0,"ExclusiveNinJas":43903,"WNType":2,"WNID":13052,"ExchangeID":0,"ExchangeCostType":0,"ExchangeCostID":0,"ExchangeCostCount":0,"JiBanJiNengIcon":["JN_06_Kazuto"],"TeshuJiNengStar":[2],"TeshuJiNengID":[4395111],"CostType":[2,2,2,1],"CostID":[6056,6057,9511,76],"CostNum":[45,3,1,2700]},{"_id":6159,"ExclusiveEquipId":6159,"ExclusiveEquipName":280000653,"ExclusiveEquipIcon":"ZSZB_Denji_02","TeshuShuXingIcon":"ZSZB_SX_02","Quality":9,"DangCi":8,"Property":4,"ExclusiveEquipMiaoShu":280001619,"MaxUPgeade":50,"QiangHua":41,"MaxStar":5,"ExclusiveEquipStarAttr":4001000,"TeshuShuXingID":60036159,"TeshuJiNengFanYiID":0,"ExclusiveNinJas":44003,"WNType":2,"WNID":13052,"ExchangeID":0,"ExchangeCostType":0,"ExchangeCostID":0,"ExchangeCostCount":0,"JiBanJiNengIcon":["JN_06_Denji"],"TeshuJiNengStar":[2],"TeshuJiNengID":[4405111],"CostType":[2,2,2,1],"CostID":[6056,6057,9511,76],"CostNum":[45,3,1,2700]},{"_id":6160,"ExclusiveEquipId":6160,"ExclusiveEquipName":280000654,"ExclusiveEquipIcon":"ZSZB_Frieren_02","TeshuShuXingIcon":"ZSZB_SX_02","Quality":9,"DangCi":8,"Property":4,"ExclusiveEquipMiaoShu":280001620,"MaxUPgeade":50,"QiangHua":43,"MaxStar":5,"ExclusiveEquipStarAttr":4001000,"TeshuShuXingID":60036160,"TeshuJiNengFanYiID":0,"ExclusiveNinJas":44103,"WNType":2,"WNID":13052,"ExchangeID":0,"ExchangeCostType":0,"ExchangeCostID":0,"ExchangeCostCount":0,"JiBanJiNengIcon":["JN_06_Frieren"],"TeshuJiNengStar":[2],"TeshuJiNengID":[4415111],"CostType":[2,2,2,1],"CostID":[6056,6057,9511,76],"CostNum":[45,3,1,2700]},{"_id":6161,"ExclusiveEquipId":6161,"ExclusiveEquipName":280000655,"ExclusiveEquipIcon":"ZSZB_Gilgamesh_02","TeshuShuXingIcon":"ZSZB_SX_02","Quality":9,"DangCi":8,"Property":5,"ExclusiveEquipMiaoShu":280001621,"MaxUPgeade":50,"QiangHua":43,"MaxStar":5,"ExclusiveEquipStarAttr":4001000,"TeshuShuXingID":60036161,"TeshuJiNengFanYiID":0,"ExclusiveNinJas":44203,"WNType":2,"WNID":13052,"ExchangeID":0,"ExchangeCostType":0,"ExchangeCostID":0,"ExchangeCostCount":0,"JiBanJiNengIcon":["JN_06_Gilgamesh"],"TeshuJiNengStar":[2],"TeshuJiNengID":[4425111],"CostType":[2,2,2,1],"CostID":[6056,6057,9511,76],"CostNum":[45,3,1,2700]},{"_id":6162,"ExclusiveEquipId":6162,"ExclusiveEquipName":280000656,"ExclusiveEquipIcon":"ZSZB_Berserker_02","TeshuShuXingIcon":"ZSZB_SX_02","Quality":9,"DangCi":8,"Property":5,"ExclusiveEquipMiaoShu":280001622,"MaxUPgeade":50,"QiangHua":43,"MaxStar":5,"ExclusiveEquipStarAttr":4001000,"TeshuShuXingID":60036162,"TeshuJiNengFanYiID":0,"ExclusiveNinJas":44303,"WNType":2,"WNID":13052,"ExchangeID":0,"ExchangeCostType":0,"ExchangeCostID":0,"ExchangeCostCount":0,"JiBanJiNengIcon":["JN_06_Berserker"],"TeshuJiNengStar":[2],"TeshuJiNengID":[4435111],"CostType":[2,2,2,1],"CostID":[6056,6057,9511,76],"CostNum":[45,3,1,2700]},{"_id":6163,"ExclusiveEquipId":6163,"ExclusiveEquipName":280000657,"ExclusiveEquipIcon":"ZSZB_Shaka_02","TeshuShuXingIcon":"ZSZB_SX_02","Quality":9,"DangCi":8,"Property":4,"ExclusiveEquipMiaoShu":280001623,"MaxUPgeade":50,"QiangHua":41,"MaxStar":5,"ExclusiveEquipStarAttr":4001000,"TeshuShuXingID":60036163,"TeshuJiNengFanYiID":0,"ExclusiveNinJas":44403,"WNType":2,"WNID":13052,"ExchangeID":0,"ExchangeCostType":0,"ExchangeCostID":0,"ExchangeCostCount":0,"JiBanJiNengIcon":["JN_06_Shaka"],"TeshuJiNengStar":[2],"TeshuJiNengID":[4445111],"CostType":[2,2,2,1],"CostID":[6056,6057,9511,76],"CostNum":[45,3,1,2700]},{"_id":6164,"ExclusiveEquipId":6164,"ExclusiveEquipName":280000658,"ExclusiveEquipIcon":"ZSZB_Lacus_02","TeshuShuXingIcon":"ZSZB_SX_02","Quality":9,"DangCi":8,"Property":5,"ExclusiveEquipMiaoShu":280001624,"MaxUPgeade":50,"QiangHua":42,"MaxStar":5,"ExclusiveEquipStarAttr":4001000,"TeshuShuXingID":60036164,"TeshuJiNengFanYiID":0,"ExclusiveNinJas":44503,"WNType":2,"WNID":13052,"ExchangeID":0,"ExchangeCostType":0,"ExchangeCostID":0,"ExchangeCostCount":0,"JiBanJiNengIcon":["JN_06_Lacus"],"TeshuJiNengStar":[2],"TeshuJiNengID":[4455111],"CostType":[2,2,2,1],"CostID":[6056,6057,9511,76],"CostNum":[45,3,1,2700]},{"_id":6165,"ExclusiveEquipId":6165,"ExclusiveEquipName":280000659,"ExclusiveEquipIcon":"ZSZB_Jinwoo_02","TeshuShuXingIcon":"ZSZB_SX_02","Quality":9,"DangCi":8,"Property":4,"ExclusiveEquipMiaoShu":280001625,"MaxUPgeade":50,"QiangHua":43,"MaxStar":5,"ExclusiveEquipStarAttr":4001000,"TeshuShuXingID":60036165,"TeshuJiNengFanYiID":0,"ExclusiveNinJas":44603,"WNType":2,"WNID":13052,"ExchangeID":0,"ExchangeCostType":0,"ExchangeCostID":0,"ExchangeCostCount":0,"JiBanJiNengIcon":["JN_06_Jinwoo"],"TeshuJiNengStar":[2],"TeshuJiNengID":[4465111],"CostType":[2,2,2,1],"CostID":[6056,6057,9511,76],"CostNum":[45,3,1,2700]},{"_id":6166,"ExclusiveEquipId":6166,"ExclusiveEquipName":280000660,"ExclusiveEquipIcon":"ZSZB_Soshiro_02","TeshuShuXingIcon":"ZSZB_SX_02","Quality":9,"DangCi":8,"Property":5,"ExclusiveEquipMiaoShu":280001626,"MaxUPgeade":50,"QiangHua":43,"MaxStar":5,"ExclusiveEquipStarAttr":4001000,"TeshuShuXingID":60036166,"TeshuJiNengFanYiID":0,"ExclusiveNinJas":44703,"WNType":2,"WNID":13052,"ExchangeID":0,"ExchangeCostType":0,"ExchangeCostID":0,"ExchangeCostCount":0,"JiBanJiNengIcon":["JN_06_Soshiro"],"TeshuJiNengStar":[2],"TeshuJiNengID":[4475111],"CostType":[2,2,2,1],"CostID":[6056,6057,9511,76],"CostNum":[45,3,1,2700]},{"_id":6167,"ExclusiveEquipId":6167,"ExclusiveEquipName":280000661,"ExclusiveEquipIcon":"ZSZB_Ainz_02","TeshuShuXingIcon":"ZSZB_SX_02","Quality":9,"DangCi":8,"Property":5,"ExclusiveEquipMiaoShu":280001627,"MaxUPgeade":50,"QiangHua":43,"MaxStar":5,"ExclusiveEquipStarAttr":4001000,"TeshuShuXingID":60036167,"TeshuJiNengFanYiID":0,"ExclusiveNinJas":44803,"WNType":2,"WNID":13052,"ExchangeID":0,"ExchangeCostType":0,"ExchangeCostID":0,"ExchangeCostCount":0,"JiBanJiNengIcon":["JN_06_Ainz"],"TeshuJiNengStar":[2],"TeshuJiNengID":[4485111],"CostType":[2,2,2,1],"CostID":[6056,6057,9511,76],"CostNum":[45,3,1,2700]},{"_id":6168,"ExclusiveEquipId":6168,"ExclusiveEquipName":280000662,"ExclusiveEquipIcon":"ZSZB_LiuDaoBan_02","TeshuShuXingIcon":"ZSZB_SX_02","Quality":9,"DangCi":8,"Property":4,"ExclusiveEquipMiaoShu":280001628,"MaxUPgeade":50,"QiangHua":43,"MaxStar":5,"ExclusiveEquipStarAttr":4001000,"TeshuShuXingID":60036168,"TeshuJiNengFanYiID":0,"ExclusiveNinJas":44903,"WNType":2,"WNID":13052,"ExchangeID":0,"ExchangeCostType":0,"ExchangeCostID":0,"ExchangeCostCount":0,"JiBanJiNengIcon":["JN_05_Madara"],"TeshuJiNengStar":[2],"TeshuJiNengID":[4495111],"CostType":[2,2,2,1],"CostID":[6056,6057,9511,76],"CostNum":[45,3,1,2700]},{"_id":6169,"ExclusiveEquipId":6169,"ExclusiveEquipName":280000663,"ExclusiveEquipIcon":"ZSZB_Kurumi_02","TeshuShuXingIcon":"ZSZB_SX_02","Quality":9,"DangCi":8,"Property":7,"ExclusiveEquipMiaoShu":280001629,"MaxUPgeade":50,"QiangHua":43,"MaxStar":5,"ExclusiveEquipStarAttr":4001000,"TeshuShuXingID":60036169,"TeshuJiNengFanYiID":0,"ExclusiveNinJas":45003,"WNType":2,"WNID":13052,"ExchangeID":6149,"ExchangeCostType":2,"ExchangeCostID":42,"ExchangeCostCount":3,"JiBanJiNengIcon":["JN_05_Kurumi"],"TeshuJiNengStar":[2],"TeshuJiNengID":[4505111],"CostType":[2,2,2,1],"CostID":[6056,6057,9511,76],"CostNum":[45,3,1,2700]},{"_id":6170,"ExclusiveEquipId":6170,"ExclusiveEquipName":280000664,"ExclusiveEquipIcon":"ZSZB_Kuririn_02","TeshuShuXingIcon":"ZSZB_SX_02","Quality":9,"DangCi":8,"Property":4,"ExclusiveEquipMiaoShu":280001630,"MaxUPgeade":50,"QiangHua":43,"MaxStar":5,"ExclusiveEquipStarAttr":4001000,"TeshuShuXingID":60036170,"TeshuJiNengFanYiID":0,"ExclusiveNinJas":45103,"WNType":2,"WNID":13052,"ExchangeID":0,"ExchangeCostType":0,"ExchangeCostID":0,"ExchangeCostCount":0,"JiBanJiNengIcon":["JN_05_SonGoku_bs"],"TeshuJiNengStar":[2],"TeshuJiNengID":[4515111],"CostType":[2,2,2,1],"CostID":[6056,6057,9511,76],"CostNum":[45,3,1,2700]}]}]],0,0,[],[],[]]
